{
  "restaurant": "멘야마쯔리",
  "place_id": "630421393",
  "collected_at": "2026-06-11T00:20:46+09:00",
  "review_type": "blog",
  "source": "place_graphql_fsasReviews",
  "cutoff_18m": "2024-12-11",
  "cutoff_24m": "2024-06-11",
  "stop_reason": "target_met:18개월이내_30개이상",
  "place_info": {
    "place_id": "630421393",
    "collected_at": "2026-06-11T00:20:46+09:00",
    "name": "멘야마쯔리",
    "category": "일본식라면",
    "address": "충남 천안시 동남구 만남로 18 휴먼빌딩 1층",
    "phone": "041-566-6907",
    "homepage": "https://www.instagram.com/menyamatsuri_no1",
    "hours": [
      {
        "day": "목",
        "open": "11:00",
        "close": "21:00"
      },
      {
        "day": "금",
        "open": "11:00",
        "close": "21:00"
      },
      {
        "day": "토",
        "open": "11:00",
        "close": "21:00"
      },
      {
        "day": "일",
        "open": "11:00",
        "close": "21:00"
      },
      {
        "day": "화",
        "open": "11:00",
        "close": "21:00"
      },
      {
        "day": "수",
        "open": "11:00",
        "close": "21:00"
      }
    ],
    "break_time": "15:00 - 16:30",
    "last_order": "20:10",
    "regular_holiday": "정기휴무 (매주 월요일)",
    "parking": "주차",
    "facilities": [
      "포장",
      "무선 인터넷",
      "남/녀 화장실 구분",
      "배달",
      "단체 이용 가능",
      "유아의자",
      "주차"
    ],
    "naver_booking": false,
    "total_visitor_reviews": 1951,
    "total_blog_reviews": 438,
    "menus": [
      {
        "name": "천안터미널 대표 해장라멘 화산라멘",
        "price": "12,000원",
        "description": "대한민국 최초! 300도 이상의 돌솥 5단계의 불타는 진한매운맛!"
      },
      {
        "name": "신부동에서 찾는 마제소바",
        "price": "10,500원",
        "description": "신개념 비벼먹는 라멘!! 부드럽고 쫄깃한 식감이 일품"
      },
      {
        "name": "천안터미널 인기 돈코츠라멘",
        "price": "9,500원",
        "description": "현지의 맛 그대로 깊고 진한 스프와 자가제면의 조합"
      },
      {
        "name": "얼큰한 카라구찌라멘",
        "price": "10,000원",
        "description": "매운맛 마니아들을 위한 1,2,3단계별 매운라멘"
      },
      {
        "name": "오코노미야끼",
        "price": "12,000원",
        "description": "철판에 구워 가쓰오부시로 풍미를 더한 오사카풍 요리"
      },
      {
        "name": "차항",
        "price": "9,000원",
        "description": "다양한 야채와 차슈를 곁들인 하카타식 찻 볶음밥"
      },
      {
        "name": "NEW!! 바사삭 볼카츠 2P",
        "price": "5,500원",
        "description": "겉바 속촉! 육즙 팡팡! 바사삭 볼카츠"
      },
      {
        "name": "교자(수제만두 6P)",
        "price": "5,500원",
        "description": "입안에서 육즙이 쫙 ~ 부드러운 교자가 한입에 쏙 ~"
      }
    ],
    "raw_hours_text": "목 11:00 - 21:00\n15:00 - 16:30 브레이크타임\n20:10 라스트오더\n금 11:00 - 21:00\n15:00 - 16:30 브레이크타임\n20:10 라스트오더\n토 11:00 - 21:00\n15:00 - 16:30 브레이크타임\n20:10 라스트오더\n일 11:00 - 21:00\n15:00 - 16:30 브레이크타임\n20:10 라스트오더\n월 정기휴무 (매주 월요일)\n화 11:00 - 21:00\n15:00 - 16:30 브레이크타임\n20:10 라스트오더\n수 11:00 - 21:00\n15:00 - 16:30 브레이크타임\n20:10 라스트오더",
    "errors": []
  },
  "reviews": [
    {
      "id": 1,
      "blog_id": "sojin_0928",
      "log_no": "224307961353",
      "url": "https://m.blog.naver.com/sojin_0928/224307961353",
      "date": "2026-06-06",
      "date_raw": "26.6.6.토",
      "title": "2026.05",
      "author": "sojin_0928",
      "body": "5월 2일 전공 수업 팀플로 팀원들과 노는 시간을 가졌다 점심시간에 만나 라멘부터 먹었다 오랜만에 멘야마쯔리에 와서 라멘 먹는데 언제 먹어도 맛있음  인생네컷도 찍고 보드게임 카페 가서 재밌게 놀았다 다음날 가족들이 내려와 같이 점심 먹었다 먹어보고 싶었던 북창동 순두부!!(BCD!) 나한테는 살짝 매웠지만 맛있었음 다 먹고 영화를 보러 갔다 기다렸던 \"악마는 프라다를 입는다 2\" 기대 가득 안고 관람했다 개인적으로 1이 좀 더 재미있었으나 2도 나쁘지 않았다. 교훈도 있고, 멋있는 장면들에서는 완전히 눈을 뗄 수 없었던..! 다 보고 나가는 길에 발견한 긴토키..! 여기서 보니 반갑구만 이건 영화 보기 전에 교보문고에서 산 굿즈 너무 귀엽고 멋있음 집으로 돌아와 가방에 달았다 애니 굿즈가 하나씩 늘어난다 (은근 가방 꾸미는 재미가 있다) 금요일 학교를 가는데 날씨가 너무 좋다 바람이 많이 불지만... 맑고 깨끗한 날이었음 수업 끝나고 더벤티에서 고구마빵과 자몽허니블랙티 시켰다 자허블 오랜만에 마시니 넘 맛있음 ☺️ 저번에 가족끼리 놀러 간 날 백화점에서 받은 시향지인데 너무 좋아서 계속 가지고 있다 유쏘풀의 \"세인트 모리츠\"라는 향이다 나중에 꼭 살 예정!! 이 향수 시향지 받은 게 정말 행운인 것 같다 이렇게 좋은 향을 알게 되다니.. ♡ 일요일 늦은 점심으로 서브밀의 브리또를 먹었다 양이 많아서 배 터지는 줄... 실습 같이 한 친구가 사준 단백질 바! 맛있음  B형 간염 백신 접종하러 보건소 왔다 친구들 말로는 엄청 뻐근하다고 하는데... 이틀차에 좀 뻐근했음 요즘 날씨 너무 더워져서 시원한 콩국수 먹었다 너무 오랜만! 고소하고 시원했다 봉사하다가 어르신께서 주신 도나스..! 백화점에서 향수 쇼핑!  며칠 전부터 아른거리던 향... Youssoful- Saint moritz 결국 샀다 탑 노트는 상큼한 자몽, 베이스 노트는 화이트 머스크가 있어 시간이 지날수록 향이 더 좋아졌다 잔향이 너무 좋아서 계속 생각났음..❤️ 만족스런 쇼핑  오랜만에 연세 빵  반쪽 얼려 먹었는데 얼먹이 너무 맛있었음! 이날은 후배님과 밥약이 있던 날! 파스타 같이 먹으며 수다 떨고 2차로 카페도 갔다 취향이 많이 겹쳐 재미있게 얘기했다  금요일 카페에 왔다 이디야에서 화채 팔길래 사 먹었다 아침 못 먹어서 크로크무슈도! 화채 시원하고 블루베리랑 수박, 망고도 있음! 토요일 봉사하러 갔다 사진촬영 담당이라 카메라를 받았다 카메라 처음 만져보는데 잘할 수 있을까 걱정됐음... 밖에 나와서 대기했다 카메라 들고 이리저리... ",
      "char_count": 937,
      "image_count": 33,
      "hashtag_count": 0,
      "has_phone": false,
      "has_naver_reservation": false,
      "recency_penalty": false,
      "weight": 1.0,
      "flags": []
    },
    {
      "id": 2,
      "blog_id": "shy_man_",
      "log_no": "224295781580",
      "url": "https://m.blog.naver.com/shy_man_/224295781580",
      "date": "2026-05-25",
      "date_raw": "26.5.25.월",
      "title": "천안 신부동 전통 일본 라멘 찐 맛집<멘야마쯔리> 거를 타선이 없다..",
      "author": "샤이맨 천안아산",
      "body": "다들 라면 좋아하시나요? 라면 한 개 쯤은 비상용으로 집에 있다 생각이 듭니다. 신라면, 진라면, 짜파게티, 팔도 비빔면 등 저희 집에는 다양한 라면들이 준비되어 있습니다. 일요일 아침으로도 종종 먹고 야식으로 라면만한게 또 없죠? 간단하지만 출출한 속을 달래주기엔 정말 없어서는 안될 필수 아이템입니다! 출처 : 네이버 플레이스 항상 맛있게 먹지만 가끔 일본 라멘이 생각이 날 때도 있어요! 녹진한 국물에 부들부들한 차슈까지 일본 라멘이 생각날때마다 전 신부동에 있는 멘야마쯔리로 향합니다 :) 알게된건 좀 오래 된거 같아요. 정확한 기간은 기억이 안나지만 5년은 넘지 않았나 싶습니다. 천안 신부동에서 이만큼 오래 있었다? 그럼 맛은 일단 보장이라고 보시면 됩니다! 아니면 버틸수가 없거등요. 오래 본 만큼 그 위치에서 처음 그 맛, 서비스로 딱 버티고 있는게 분명합니다. 출처 : 네이버 플레이스 멘야마쯔리 신부점 추천 메뉴  1. 화산라멘  2. 돈코츠라멘  3. 오코노미야끼 최애 화산라멘은 비주얼부터 압도적 돌솥에 보글보글 끓으면서 나오는데 비주얼이 진짜 시선 강탈! 맵기는 너무 자극적인 느낌보다는 칼칼하고 중독성 있는 맛! 먹다 보면 땀이 송글송글 나는데 계속 국물 떠먹게 되는 맛  진한 국물이 매력적인 돈코츠라멘 국물 한입 먹자마자 느껴지는 진한 돈코츠 풍미…  너무 느끼하지 않고 깔끔한 스타일이라 끝까지 부담 없이 먹기 굳 면도 자가제면 느낌이라 쫄깃했고 차슈도 부드러워서 국물이랑 정말 잘 어울렸어요. 사이드 메뉴로 꼭 추천하고 싶은 오코노미야끼 ✨ 라멘만 먹기 아쉬워서 같이 주문한 오코노미야끼! 처음 나왔을 때 비주얼부터 완전 일본 느낌 한입 먹어보니까 겉은 살짝 바삭하고 안은 촉촉하면서 양배추 식감이 살아 있어서 좋았어요. 특히 달달짭짤한 소스랑 마요네즈 조합이 진짜 최고… 라멘 국물이랑 같이 먹으니까 궁합도 잘 맞더라구요. 생각보다 양도 꽤 있어서 사이드 메뉴인데도 만족감이 큰 메뉴! 출처 : 네이버 플레이스 테이블 기본 세팅도 좋았던 곳 테이블마다 통마늘, 깨, 생강 등이 준비되어 있어서 취향대로 넣어 먹을 수 있는 점도 좋았어요. 특히 직접 마늘을 으깨 넣어 먹는 재미가 있어서 국물 풍미가 훨씬 살아나는 느낌!  추천 조합 ✨ 얼큰하게 먹고 싶다면 → 화산라멘 + 교자 처음 방문이라면 → 돈코츠라멘 + 미니차슈덮밥 든든하게 먹고 싶다면 → 마제소바 + 밥추가 총평 ✨ 천안 신부동에서 일본식 라멘 제대로 먹고 싶다면 멘야마쯔리 신부점 추천! 진한... ",
      "char_count": 914,
      "image_count": 1,
      "hashtag_count": 0,
      "has_phone": false,
      "has_naver_reservation": false,
      "recency_penalty": false,
      "weight": 1.0,
      "flags": []
    },
    {
      "id": 3,
      "blog_id": "piglet-b-",
      "log_no": "224295745389",
      "url": "https://m.blog.naver.com/piglet-b-/224295745389",
      "date": "2026-05-25",
      "date_raw": "26.5.25.월",
      "title": "천안ㅣ신부동 라멘 멘야마쯔리 신부점 내돈내산 천안터미널 해장 음식 점심 혼밥 맛집 추천 주차",
      "author": "Piglet",
      "body": "멘야마쯔리 신부점 ⏱️매일 11:00-21:00 (L.O 20:10) Break Time 15:00-16:30 매주 월요일 정기휴무  가게 주차장 없음 신부 제5공영주차장 이용 (1시간 무료)  남녀 구분 / 가게 외부 위치 Instagram: @menyamatsuri_no1 ☎️ 0507-1371-4710 천안 신부동 라멘 점심 맛집 멘야마쯔리 신부점 주차장 안내 인근 신부 제5공영주차장 이용 추천 (도보1분) 주차요금 가게 이용 시 1시간 무료 최초 30분 무료 30분 초과 시 10분마다 200원 2시간 초과 시 10분마다 300원 (1시간 1,200원-1,800원으로 아주 저렴) 가게 주차장이 따로 있지는 않아서 새로 생긴 신부 제 5공영주차장 이용하면 됨 도보로 1분이라 걸어서 갈 수 있고 가게에 이야기 하면 1시간 무료 가능합니다 외관 신부동 먹자골목쪽에 위치한 오래된 라멘맛집 예전에 처음 천안으로 왔을 때 가끔 혼밥을 했던 곳인데 오랜만에 라멘이 먹고 싶어서 방문하게 됐어요 내부 테이블이 7개정도 있고 2인/4인 테이블이 섞여 있습니다 2인 테이블에서는 혼밥도 할 수 있어서 부담없음 출처: 네이버 가게 메뉴 이미지 시그니처메뉴는 해장 제대로 되는 매콤한 화산라멘이고 오리지널메뉴로 돈코츠라멘이 있습니다 리뷰이벤트를 하면 음료수,아지타마고,차슈3p 중 1개 제공 평일 런치타임 (11시-15시) 1인 1식할 경우 라멘 사이즈업 서비스 주문 시 라지 옵션 선택 (정식메뉴는 사이즈업 불가) 점심시간에 가면 런치할인 세트메뉴도 있고 1인 1식하면 라멘 사이즈를 무료로 업해준다고 합니다 남자들은 양 부족하면 점심시간에 이런 이벤트 이용하면 좋을듯 주문은 테이블오더로 하면 됩니다 Order List 화산라멘 11.0 돈코츠라멘+볼카츠 2pc 세트 13.9 테이블에는 라멘과 같이 먹을 수 있는 일본식 단무지?가 있고 (안먹어봐서 모르겠음) 통깨, 후추, 마늘이 있습니다 마늘은 테이블에 있는 압축다지기로 다져서 라멘에 넣어서 먹어주면 됨 화산라멘 (11.0) 시그니처메뉴라고 해서 해장도 할 겸 화산라멘 주문 돌솥에 국물을 눈앞에서 넣고 뚜껑을 덮어줍니다 화산라멘이라 그런지 위로 연기가 푱푱 빠져나감 3분 모래시계를 주는데 시간이 끝나면 직원분께서 나머지 국물을 다 부어주면 먹으면 됩니다 화산라멘 (11.0) 레벨 3 짜릿하게 즐기는 맛 공기밥 반공기 무료 제공 화산라멘은 5단계의 매운맛을 선택할 수 있는데 3단계가 짜릿하게 즐기는 맛이라고 해서 주문했는데 생각보다 많이 매웠어요 3단계가 틈새라면 정도의 맵기 맛있게 먹으려면 2단계가 딱 적당할거 같음 맵찔이는 애초에 그냥... ",
      "char_count": 996,
      "image_count": 19,
      "hashtag_count": 0,
      "has_phone": true,
      "has_naver_reservation": false,
      "recency_penalty": false,
      "weight": 1.0,
      "flags": []
    },
    {
      "id": 4,
      "blog_id": "mattopia",
      "log_no": "224224549442",
      "url": "https://m.blog.naver.com/mattopia/224224549442",
      "date": "2026-03-25",
      "date_raw": "26.3.25.수",
      "title": "멘야마쓰리 신부점 평범하고 편한 프렌차이즈 일본 라멘집",
      "author": "맛토",
      "body": "천안이다. 신부동 문화거리의 라멘집에 다녀왔다. 천안에서 출발해 전국으로 퍼져나간 라멘 브랜드. 멘야(麺屋)와 마쯔리(祭り), 면과 축제의 결합이라는 단순한 조합은 의외로 직관적이다. ‘라멘 축제’ 자가제면을 내세운다는 점에서 ‘면’에 대한 자부심이, 그리고 북적이는 매장 풍경에서 ‘축제’의 기운이 자연스럽게 이어진다. 실제로 매장은 넓지 않은 편이다. 다찌 좌석 없이 주방과 테이블 위주로 구성된 구조라 동선은 간결하지만, 점심시간에는 빈틈을 찾기 어려울 정도로 사람들로 채워진다. 어깨를 살짝 좁히고 자리를 잡는 순간, 이곳이 일상의 한복판에 놓인 작은 식당이라는 사실이 더 분명해진다. 주문은 카라구찌 라멘 2단계로 선택했다. 2단계가 신라면 정도라 했다. 매운맛을 1, 2, 3단계로 나눈 구성은 취향에 맞게 접근할 수 있다. 가격은 10,000원. 차슈 세 장과 반쪽 계란이 올라간 구성은 단정하면서도 익숙하다. 잘 못 찍힌 사진, 면발은 얇은 편이다. 카라구찌 라멘의 맛은 전반적으로 균형이 무난한 일본식 라멘에 가깝다. 신라면 정도의 자극으로, 국물의 진득함을 해치지 않으면서 끝맛에 가벼운 열감을 남긴다. 차슈는 과하게 기름지지 않고 적당히 풀어지며, 면은 부드럽게 넘어간다. 전체적으로 튀지 않고 안정적인 맛이라 호불호 없이 받아들여질 스타일이다. 함께 주문한 군만두(사진없음)는 바삭하게 구워진 표면과 균일한 형태가 어딘가 익숙하다 했더니, 자연스럽게 예전 기억이 겹친다. 다른 라멘집에서 “이거 직접 만드시나요?”라고 물었다가 “비비고예요”라는 답을 들었던 장면이 떠오른다. 이번에도 비슷한 결이다. 특별함을 기대하기보다는, 그냥 편하게 곁들이는 사이드 메뉴라는 정도의 의미에 가깝다 그런데 비비고가 만두를 참 잘 만들긴 한다. 멘야마쯔리 신부점은 어떤 대단한 한 끼를 기대하고 찾기보다는, 일상 속에서 무난하게 스며드는 식사에 가깝다. 직장 동료들과 길게 고민하지 않고 들어가, 적당히 만족스럽게 먹고 나오는 흐름. 간편한 혼밥 장소로도 잘 맞는다. 이곳의 ‘축제’는 거창하지 않다. 일상이 축제인가? 해피축제",
      "char_count": 795,
      "image_count": 7,
      "hashtag_count": 0,
      "has_phone": false,
      "has_naver_reservation": false,
      "recency_penalty": false,
      "weight": 1.0,
      "flags": []
    },
    {
      "id": 5,
      "blog_id": "jin_mdmh",
      "log_no": "224190711231",
      "url": "https://m.blog.naver.com/jin_mdmh/224190711231",
      "date": "2026-02-21",
      "date_raw": "26.2.21.토",
      "title": "천안터미널 신부동 라멘 내돈내산 맛집: 멘야마쯔리 신부점",
      "author": "찌니",
      "body": "오늘 점심은 라멘이다! 싶었는데 천안 터미널엔 라멘집이 몇 개 없더라고요? 어디갈까~~~하다가 #멘야마쯔리 로 가보기루! ⏰️영업시간 화수목금토일 11:00 - 21:00 15:00 - 16:30 브레이크타임 20:10 라스트오더 매주 월요일 정기휴무 주소 충남 천안시 동남구 만남로 18 휴먼빌딩 전화번호 041-566-6907 주차 신부 제5공영주차장 이용 천안터미널에서 5분 정도 걸어오면 멘야마쯔리 도착! 중간에 비슷하게 생긴 다른 라멘집이 있어서 다른데 갈뻔ㅋㅋㅋㅋ 주방은 오픈 주방이예요:) 주문은 키오스크로! 저흰 돈코츠 라멘, 카라구찌 라멘, 교자 주문했습니다 원래 화산라멘 궁금해서 먹으러 온건데 이 날만 그런건지 메뉴에서 빠진건지 키오스크에 없더라구요? (´･ｪ･｀) 세트도 구성 좋아요 히히 맛있겠당 근데 모든 메뉴가 같이 나왔는데, 교자는 미리 구우셨는지 식어서 왔더라고요 조금 아쉽,,,, 카라구찌 라멘! 2단계라 적당히 매콤칼칼한 맛 근데 캡사이신 맛이 조금 자극적이어서 갠적으론 돈코츠가 더 내 취향이었다는ㅎㅎ 근데 다른 후기들 보니까 1단계 시키면 더 맛있다더라고요? 담에 다시 도전해보기로...(ง˙∇˙)ง 그리고 처음엔 양이 적은가? 싶었는데 생각보다 면이 많이 들어있어요 배터져부러~~~ 열심히 마늘 으깨는 우리집 토핑쟁이♪ 구운 계란이 올려져 있어서 완숙 계란인가? 했는데 반숙 완벽하더라구요 쫄깃촉촉 넘 맛있당 대체 어떻게 만든거지...?! 후식으로 피붕&김붕까지 완벽~~~!❤️",
      "char_count": 581,
      "image_count": 10,
      "hashtag_count": 1,
      "has_phone": true,
      "has_naver_reservation": false,
      "recency_penalty": false,
      "weight": 1.0,
      "flags": []
    },
    {
      "id": 6,
      "blog_id": "sighting_",
      "log_no": "224182036277",
      "url": "https://m.blog.naver.com/sighting_/224182036277",
      "date": "2026-02-13",
      "date_raw": "26.2.13.금",
      "title": "[ 천안 신부동 맛집 ] 비오는 날 라멘 데이트 \"멘야마쯔리\"",
      "author": "현현",
      "body": "멘야마쯔리 # 터미널 # 비 오는 날 # 라멘 천안 놀러 온 남자친구랑 천안 터미널 가까운 곳에서 가볍게 먹기 위해 들어간 곳 살짝 비가 와서 급하게 찾아서 들어가 본 곳인데 점심시간이라 그런지 사람들이 계속 들어오더라고요. 재밌게도 버스터미널을 오가면서 스쳤던 사람들과 동선이 겹쳐서 옆자리에서 마주치는 일도 있었답니다. 기본 정보 월요일 정기휴무 운영시간 11:00-21:00 브레이크 타임 15:00-16:30 라스트오더 20:10 주차 - 신부제5공영주차장 ( 1시간 ) 내부 가게 내부는 아늑한 느낌이라 편하게 앉아서 식사하기 좋았어요. 그리고 테이블 배치가 혼자 와도 어색하지 않은 구조라 혼밥하기에도 자연스러운 느낌이에요. 점심시간이고 가게가 큰 편이 아님에도 회전율이 빠른 느낌이라 손님들이 대기 없이 바로 들어오더라고요. 또한 주변을 둘러보면 일본어로 된 문구들이 보여서 일본에 온 듯한 느낌을 줬어요. 테이블에 앉으면 기본으로 컵, 국그릇, 깨, 후추, 생강 절임, 마늘이 배치되어 있었습니다. 메뉴판&메뉴 저희는 돈코츠 차항 세트(13,400원)랑 카라구찌 규동 세트(13,400원) 이렇게 두 가지를 주문했어요. 세트 메뉴라 구성이 든든해서 한 끼 식사로 충분했습니다. 먼저 돈코츠 라멘은 국물에서 깨가 들어간 듯한 고소한 향이 은근히 느껴졌어요. 맑은 스타일이라기보다는 묵직하고 진한 쪽에 가까워서 한 입 먹자마자 “아, 일본 라멘 느낌이다” 싶더라고요. 카라꾸찌 라멘은 신라면 정도의 맵기로 주문했는데, 맵기 조절이 3단계까지 가능해서 취향에 맞게 선택할 수 있었어요. 라멘 위에는 계란, 차슈, 숙주, 파가 적당히 올라가 있어서 푸짐해 보였고, 특히 차슈는 두툼하면서 살짝 불향이 느껴져 만족스러웠습니다. 차항은 이번에 처음 먹어봤는데 일본식 중화 볶음밥이라고 하더라고요. 고슬고슬하게 볶아진 기본 스타일의 볶음밥이라 라멘이랑 같이 먹기 부담 없었어요. 규동은 촉촉하면서 단맛이 은근히 느껴졌고, 올라간 파향이 잘 어울려 전체적으로 밸런스가 좋았습니다. 전체적으로 맛은 깔끔하고 가벼운 느낌보다는 고소하고 묵직한 쪽에 가까웠어요. 진한 국물 좋아하는 분들이라면 만족할 스타일이라는 생각이 들었습니다. 서비스/특징 기억에 남는 점은 라멘이 나왔을 때 수저 방향이 살짝 반대로 놓여 있었는데, 직원분이 바로 알아보시고 예쁜 방향으로 정리해 주시더라고요. 작은 부분이지만 이런 세심한 배려 덕분에 괜히 기분이 좋아졌습니다. 또한 차슈, 계란, 음료 중... ",
      "char_count": 941,
      "image_count": 12,
      "hashtag_count": 0,
      "has_phone": false,
      "has_naver_reservation": false,
      "recency_penalty": false,
      "weight": 1.0,
      "flags": []
    },
    {
      "id": 7,
      "blog_id": "jjtup",
      "log_no": "224172047777",
      "url": "https://m.blog.naver.com/jjtup/224172047777",
      "date": "2026-02-05",
      "date_raw": "26.2.5.목",
      "title": "천안 신부동 라멘 멘야마쯔리",
      "author": "보니유니",
      "body": "라멘 좋아함. 소유라멘 최애임. 터미널 라멘집 검색하면 멘야마쯔리 존맛탱집이래서 가봄~ 소유라멘이 읍드라. 내부 좁아효 화장실 뒷문으로 나가서 앞에 건물로 드가면 됨 비번 있었던듯 휴지 챙겨가야함. 돈코츠 먹었눈뎅 넹 맛있었어여 개존맛탱 천안 라멘 원탑 이정돈 아니고 그냥. 음~맛있넹 정도? (대각선 테이블 잼민이 연애썰이 더 맛있긴했음) 일단 소유라멘 없어서 앞으로는 안 갈듯",
      "char_count": 163,
      "image_count": 6,
      "hashtag_count": 0,
      "has_phone": false,
      "has_naver_reservation": false,
      "recency_penalty": false,
      "weight": 1.0,
      "flags": [
        "extraction_warning:163자"
      ]
    },
    {
      "id": 8,
      "blog_id": "rangicute",
      "log_no": "224161159470",
      "url": "https://m.blog.naver.com/rangicute/224161159470",
      "date": "2026-01-27",
      "date_raw": "26.1.27.화",
      "title": "[맛집] 천안 멘야마쯔리 신부점",
      "author": "장멍멍",
      "body": "남편이랑 아바타 막차를 타기위해 진짜 오래간만에 천안 터미널로 나왔다. 만두전골 / 쌀국수 / 햄버거 / 칼국수 등등등 먹을거는 엄청 많이 있었느나 옛날 연예할때 멘야 마쯔리 쌍용동에서 먹은 기억에 추억 돋게 라멘으로 결정 3년은 더 되었나 보다. 천안 터미널로 나오니 오랜만에 사람구경도 하고 바뀐상가도 구경하고 가는길이 눈이 질퍽에서 길이 미끄러워 조금 그랫지만 설레임이 가득햇다. 들어가면 사이드에 향신료 생강절임 ? 마늘 등과 컵이 있다. 젓가락과 마늘 으깨는거 그리고 티슈는 옆에를 열면 있다. 근데 마늘을 한번도 안넣어먹어바서 ;; 그럼 맛이 세배가 대나 ? 어떤음식에 넣어 먹는거지하고 궁금증만 증폭 ㅋㅋㅋ 다른블로그에서는 라멘에 마늘꼭 넣어 먹으라는데 보고갈껄 ㅋㅋㅋㅋ 시도하기에는 자신감이 없엇다. 다음에는 꼬옥 마늘 넣어 먹어 바야지 -__- 카라구찌라멘+볼카츠 2PC 와 돈코츠라멘 을 주문 옛날에는 오코노미야끼랑 세트도 있던거 같았는데 아쉬웠다.ㅠㅠ 하지만 맛은 역시 면부터 틀리고 라멘국물도 진하니 맛있다. 일본여행을 안가본 1인으로써 진정한 라멘을 한국에서 만났다.ㅋㅋㅋㅋㅋ 일본라멘도 똑같겠지? ㅋㅋㅋㅋㅋㅋ 볼카츠는 고급진 동그랑땡 맛같았는데 생각을 해보니 어디선가 먹어본 그런맛 근데 기억은 안나고 ㅋㅋㅋㅋㅋ 면이랑 차슈랑 먹고 국물 먹고 무한 반복하다가 마무리로 볼카츠를 레몬즙뿌려 먹어버리면 ㅋㅋㅋㅋㅋ 요래요래 싹싹 비우게 된다. 테이블은 조금 좁은 편이긴 하다. 우리가 거의 마지막 오더 할때쯤 갔는데도 사람이 많이 있었다. 대략 여섯자리인데 3테이블에 젊은 커플이 또 다시들어온 테이블에도 젋은 남녀가 우리가 제일 나이들어 보엿 ㄷㄷㄷㄷㄷㄷㄷㄷㄷㄷ 젋은이들의 맛집이 틀림 없다. 그래서 젋은 기운을 듬뿍 받아 왔다.ㅋㅋㅋㅋㅋ 가게 직원분들도 친절하고 마직막 오더에는 마지막 오더라고 테이블 마다 친절하게 여쭤바주시고 서비스도 맛도 만족스런운 곳이었다. 그럼 맛있게 먹었으니 그다음 행선지인 붕신으로 ㄱㄱㄱㄱ 지극히 개인적인 입맛으로 추억의 국물이 진국인 라멘 맛집 ★★★★☆",
      "char_count": 782,
      "image_count": 5,
      "hashtag_count": 0,
      "has_phone": false,
      "has_naver_reservation": false,
      "recency_penalty": false,
      "weight": 1.0,
      "flags": []
    },
    {
      "id": 9,
      "blog_id": "kamu_",
      "log_no": "224150155028",
      "url": "https://m.blog.naver.com/kamu_/224150155028",
      "date": "2026-01-18",
      "date_raw": "26.1.18.일",
      "title": "천안 맛집 멘야마쯔리 내돈내산후기 일식 라멘 마제소바 전문점 천안 점심 신부동 맛집 천안 고속버스터미널 주변 맛집",
      "author": "연하루",
      "body": "천안 맛집 멘야마쯔리 내돈내산후기 일식 라멘 마제소바 전문점 천안 점심 신부동 맛집 천안 고속버스터미널 주변 맛집 이번에 남자친구와 함께 천안 여행을 다녀왔는데요. 점심 메뉴를 고민하던 중, 남자친구가 천안 고속버스터미널 근처에 멘야마쯔리라는 일식 맛집이 있다고 알려줘서 방문하게 되었어요. 웨이팅을 할 정도로 찐 맛집이라는 얘기를 듣고 기대감을 한가득 안고 찾아갔답니다. 위치: 충남 천안시 동남구 만남로 18 휴먼빌딩 1층 신부동 터미널 건너편 9가지 치과 뒷편으로 오면 보입니다! 영업시간 화 ~ 일 11:00 ~ 21:00 브레이크타임 15:00 ~ 16:30 라스트오더 20:10 매주 월요일 정기휴무 주차 정보 신부 제5공영주차장 이용 1시간 무료 주차 가능 메뉴판 & 주문 멘야마쯔리 메뉴판을 보니 오꼬노미야끼를 반으로 잘라서 판매하고 있더라구요! 항상 메인 메뉴에 사이드까지 먹고 싶어도 배가 불러서 잘 못 먹는 저희 커플에게는 정말 반가운 이야기였어요. 저희는 수요일 오전 11시에 방문했는데요. 웨이팅 없이 바로 들어갈 수 있었습니다. 테이블마다 태블릿 주문이라 주문도 편했습니다. 저희가 주문한 메뉴는 돈코츠라멘 9,500원 마제소바 10,500원 반달야끼 6,500원 총 26,500원! 가격도 부담스럽지 않고 적당한 편이었어요. 가게 분위기 가게 내부는 일식집답게 일본 노래가 흘러나오고 일본어로 된 문구들이 가득했어요. 오타쿠 감성인 저희 커플에게는 너무 잘 맞는 분위기였습니다. 다만 아쉬운 점은 가게가 생각보다 아담한 편이라는 점! 테이블 수가 많지 않고 테이블 간 간격이 조금 좁아서 약간은 불편하게 느껴졌어요. 테이블에는 깨, 생강절임, 통마늘, 후추가 준비되어 있었고 통마늘은 마늘 빻는 도구로 직접 빻아 먹을 수 있었어요. 마제소바 & 돈코츠라멘 & 반달야끼 맛 후기 먼저 남자친구가 주문한 마제소바가 나왔어요. 마제소바를 다 먹고 나서 비벼 먹을 수 있는 밥도 요청하면 무료로 주시더라구요. 잔뜩 올라간 대파, 신선한 노른자, 고소한 들깨가루가 비주얼부터 인상적이었어요. 식초도 함께 주셨는데 원하는 만큼 뿌려 먹으면 된다고 하셔서 식초를 좋아하는 남자친구가 약 세 바퀴 정도 넉넉하게 뿌렸답니다. 근데 전혀 시지 않고 오히려 고소하더라구요. 숟가락으로 열심히 비벼 한 입 먹어보니 고소한 들깨가루와 아삭한 파 식감이 어우러져 정말 맛있었어요. 저는 마제소바를 아주 좋아하는 편은 아니라 잘하는 집 아니면 잘 안 시켜 먹는데 여기 마제소바는 제가 먹어본 마제소바 중 단연코 1등이었어요.... ",
      "char_count": 953,
      "image_count": 33,
      "hashtag_count": 0,
      "has_phone": false,
      "has_naver_reservation": false,
      "recency_penalty": false,
      "weight": 1.0,
      "flags": []
    },
    {
      "id": 10,
      "blog_id": "dolidoli-",
      "log_no": "224137394829",
      "url": "https://m.blog.naver.com/dolidoli-/224137394829",
      "date": "2026-01-07",
      "date_raw": "26.1.7.수",
      "title": "추운 겨울 신부동 가성비 라멘 맛집 | 멘야마쯔리 신부점",
      "author": "도리",
      "body": "안녕하세요! 저는 새해에도 여전히 학원을 다니고 있어요ㅋㅋㅋㅋ! 새해 첫 학원 가는 날은 도시락을 싸고싶지 않아서... 외식을 하자! 하고 날이 너무 추워 뜨끈한 국물이 있는 멘야마쯔리로 향했습니다! 멘야마쯔리 신부점 충남 천안시 동남구 신부동 454-1 매일 11:00 - 21:00 15:00 - 16:30 브레이크타임 20:10 라스트오더 (매주 월 정기휴무) 0507-1381-6907 신부 제 5공영주차장 1시간 주차권 가능 날이 너무 추워서 깜빡잊고 외관사진을 찍지 못했지만...! 신부 제 5 공영주차장에서 먹자골목 쪽으로 걸어오시면 어렵지 않게 찾을 수 있어요! 내부에는 사람이 많아서 사진을 찍진 못했어요! 다찌석은 따로 없었고, 전부 테이블석이였습니다 제가 앉은 자리에서는 저런 벽면이 보이더라구요ㅋㅋㅋ 기본세팅은 후추와 마늘, 참깨, 물, 생강절임이 있었습니다! 주문은 각 테이블에 설치되어있는 키오스크를 이용하시면 됩니다! 평일 런치타임 (11:00 - 15:00)에는 무료 라멘 사이즈업을 해주시더라구요! 오늘 배가 좀 많이 고프다! 하시는 분들께 추천하는 이벤트였습니다 카라구찌 라멘 (\\9,500) / 하카타 돈코츠 라멘 (\\9,000) 저희가 시킨 라멘 입니다 계란과, 챠슈, 숙주 등이 어우러져 깊고 시원한 맛을 내는 국물이 아주 맛있었어요! 저는 카라구찌 라멘을 시켜서 먹었습니다. 매운맛은 1단계로 시켰어요! 예전에 같은 체인점에서 2단계를 먹었던 기억이 있는데, 그때 2단계는 너무 캡사이신 맛이 강해서 라멘의 국물맛이 안나고, 그냥 무식하게 맵기만 했어서 이번에는 1단계로 했더니 딱 좋았어요! 라멘의 맛도 느끼고, 매운맛도 있었으면 좋겠다 하시면 1단계 추천드립니다! 차슈가 두툼하고 맛있었어요! 은은한 불향도 느껴져서 라멘국물에 적셔먹으니 너무너무 맛있더라구요! 질기거나 하는 부분없이 부드럽고 좋았습니다! 면발도 푹 퍼지거나, 덜 익은 부분없이 전체적으로 다 잘 익어있어서 후루룩 먹기 좋았습니다! 국물과 같이 먹으니 뜨끈하고 너무 좋았어요 반숙란을 제일 처음 먹었는데, 너무 차가웠어요ㅜㅜ 다른곳은 그래도 따뜻하게 먹었어서 그런지 딱 처음 먹고 차가워서 어...? 하면서 당황했었네요ㅋㅋㅋ 반숙란도 맛은있었지만, 바로 먹으면 좀 차가우니 국물안에 조금 넣었다가 먹으면 좀 더 따뜻해져서 더 맛있었겠다...! 하는 생각이 들었습니다! 멘야마쯔리는 거의 대부분의 메뉴가 만원이 넘지 않아서 가성비 외식 메뉴로 딱 이라는 느낌이 들었어요! 신부동에 위치한 멘야마쯔리는 가게는 조금 작지만, 그래도... ",
      "char_count": 977,
      "image_count": 12,
      "hashtag_count": 0,
      "has_phone": true,
      "has_naver_reservation": false,
      "recency_penalty": false,
      "weight": 1.0,
      "flags": []
    },
    {
      "id": 11,
      "blog_id": "jjuster",
      "log_no": "224135975313",
      "url": "https://m.blog.naver.com/jjuster/224135975313",
      "date": "2026-01-06",
      "date_raw": "26.1.6.화",
      "title": "천안 멘야마쯔리 신부점 화산 라멘 (주차 본점 포장 맵기 등)",
      "author": "쭈스터",
      "body": "친한 친구가 천안으로 이사를 가버렸다... 이대로 친구를 잃을 순 없어! 하고 찾아갔다. 천안 나들이 중 화산 라멘을 알게 되었다. 시선 집중돼서 아주 조금은 창피했지만 이내 개의치 않고 먹었다. 결과적으로 만족! 천안 멘야마쯔리 화산라멘 화산 라면 일단 천안 멘야마쯔리 화산라멘 처음 나오는 비주얼은 이렇다. 무슨 솥이 나와서 사실 놀랐다... 모래시계를 같이 주는데 모래가 다 소진되면 솥뚜껑을 열면 된다. (직원분이 직접 오셔서 열어줌) 먹는 입장에서 재미있었다. 모래 떨어지는 거 보면서 불멍 아닌 모래멍 하고 있으면 시간도 금방 간다. 화산 라멘 맵기 선택 1단계 덕유산 부담없이 매콤한 맛 2단계 설악산 맛있게 매운 맛 3단계 지리산 짜릿한 매운 맛 4단계 한라산 고통스러운 매운 맛 5단계 백두산 폭발적인 매운 맛 순으로 맵다. 매운맛 마니아는 아니라서 3단계 지리산 맛으로 주문하고도 꽤나 매워했던 것으로 기억한다 ㅋ * 솥뚜껑 위에 뜨거운 김이 나오니 조심해야 한다. 화산라면 쫘잔 ,, 구운 달걀도 넣어주는 라멘 집이다. 차슈는 세 점 들어있다. 하나는 그냥 먹고, 하나는 면이랑 먹고, 나머지 하나는 제일 맛있었던 조합으로 먹긔 ★ 차슈 튀김 작은 종지 그릇에 차슈 튀김도 같이 주는데 라멘에 곁들여 먹으면 맛이 괜찮다. 국물 맛이 진해지는 느낌 ㅎ_ㅎ 카라구찌라멘 친구는 카라구찌 라멘을 시켰다. 매운맛 마니아들을 위한 라멘이다. 친구는 2단계인가 시켰던 것 같다. 근데 글 쓰는 지금 왜 이게 더 맛있어 보이는지...? 다음에 먹어봐야겠다. 멘야마쯔리 주차 본점 주차는 모르겠지만 내가 간 신부점 주차 여부 알려드리겠다. 바로 옆에 공영주차장이 있어서 거기에 주차하고 가게에 말하면 주차 시간을 넣어준다. 생각보다 공간이 넓지는 않으니 참고하시길! 멘야마쯔리 포장 배달 멘야마츠리 포장, 배달 둘 다 가능하다. 나는 매장에서 먹었는데 먹는 동안 배달 알림음이 많이 울렸다 ㅎ_ㅎ 멘야마쯔리 본점 멘야마쯔리는 신부점 말고도 청당점, 쌍용본점, 성성점, 아산탕정점 등 여러 개 지점이 있던데, 천안 어디서나 만날 수 있는 라멘 집인 것 같다. 막 엄청나게 특별한 맛은 아니지만 지나가다 본다면 또 들릴 의향 있다. 이상 멘야마쯔리 내돈내산 리뷰였다! 술 먹고 해장하기에도 참 좋은 곳인 듯",
      "char_count": 838,
      "image_count": 4,
      "hashtag_count": 0,
      "has_phone": false,
      "has_naver_reservation": false,
      "recency_penalty": false,
      "weight": 1.0,
      "flags": []
    },
    {
      "id": 12,
      "blog_id": "dbstnwls97",
      "log_no": "224093038826",
      "url": "https://m.blog.naver.com/dbstnwls97/224093038826",
      "date": "2025-11-30",
      "date_raw": "25.11.30.일",
      "title": "천안 신부동 맛집 뚜딘픽 “멘야마쯔리 신부점”",
      "author": "뚜딘",
      "body": "안녕하세요 뚜딘 입니다 :) 이번에 소개할 맛집은 \"맨야마쯔리 신부점\" 입니다 ❤︎ 멘야마쯔리 신부점 ❤︎ “면의축제” 겨울철 온도가 낮아지고 세찬바람이 불어올때 ! 주인장 뚜딘의 소울푸드 라멘이 생각나는데요 신부동에서 제입맛에 딱 맞는 라멘집 뚜딘의 n번째 방문 ! 또간집으로 낋여왔습니다  매장운영시간 화-일 11:00-21:00 월요일 정기휴뮤 브레이크타임 15:00-16:30 라스트오더 20:10  매장 외부 교토같은 일본감성의 외부입니다 ㅎㅎ 오래된 신부동 맛집으로 신부동에 방문하셨다면 누구나 한번쯤 봤을 라멘집 !! 매장앞에는 이벤트 배너가 크게 놓아져있습니다 평일런치타임11:00-15:00 방문시 메인메뉴와함께 사이드를 함께 먹을수있는 런치세트를 할인된 가격으로 판매하고있습니다 매장 내부 일본느낌의 아담하지만 깔끔한 내부! 오픈주방으로 조리하는 모습도 한눈에 보이는데요!! 토요일 2시에 방문했을때 정말 사람이 바글바글 웨이팅 맛집 ❤︎ 멘야마쯔리 신부점 ❤︎ 웨이팅1팀이었어서 바로 입장했어요 (다행) 점심시간이 지나도 브레이크타임 전까지 바글바글 ❤︎ 멘야마쯔리 신부점 ❤︎ 화장실은 나가서 쭈욱 - 건물안에 있습니다! 12시간 이상 과정을 통해 1그릇에 담은 정성  ❤︎ 멘야마쯔리 신부점 ❤︎ 저는 혼자 방문했는데 여기 혼밥 하기 너무 쉬운 레벨  혼자와서 라멘 호로록~ 매뉴 돈코츠라멘 카라구찌라멘 마제소바 등등 정말 다양한 일본식라멘이 있고 사이드도 많아요 네이버 리뷰작성시 , 아지타마코(반숙계란) or 차슈3장 or 음료수 택1  카라구찌 라멘 10,000 매운맛 2단계 (신라면 2-3배 정도) 주문후 10분내외로 나왔습니다 빨강국물로 침샘폭발 비주얼  차슈도 두툼하고 너뮤 맛나보이는 비주얼 ✨ 검은깨가 톡톡 ! 파랑 숙주도 가득해요 !! 이 면식감이 특이해서 라멘을 찾는데요 한국인 입맛에 딱 좋은 면발이고 국물이 진하고 느끼하지않아 너무 맛있어요 ㅠㅠ ❤︎ 멘야마쯔리 신부점 ❤︎ 차슈랑 면 듬뿍 퍼먹기 ! 신라면 맵기보다 2-3배인데 저한테 딱 좋았어요 ! 느끼함도 없고 국물의 진함 그리고 불맛의 매콤함  아지타마코(반숙계란)도 아주 딱 알맞게 익어 매울때 한입 먹으면 매운맛 중화 시켜줍니다 저는 초생강도 필요없고 단무지도 필요없다고 느꼈어요 단일메뉴만 먹어도 맛있는 카라구찌라멘 ❤️ 완뚝 완료 ~~ 양도 많아서 정말 한그릇 다 먹으면 저녁때까지 배불러요 ㅠㅠ ❤️❤️❤️ 돈코츠라멘도 마제소바도 맛있었지만 저는 카라구찌라멘이 1등 !!!... ",
      "char_count": 951,
      "image_count": 33,
      "hashtag_count": 0,
      "has_phone": false,
      "has_naver_reservation": false,
      "recency_penalty": false,
      "weight": 1.0,
      "flags": []
    },
    {
      "id": 13,
      "blog_id": "hison93",
      "log_no": "224081493819",
      "url": "https://m.blog.naver.com/hison93/224081493819",
      "date": "2025-11-19",
      "date_raw": "25.11.19.수",
      "title": "[천안먹거리] 멘야마쯔리 신부점 다녀왔어요",
      "author": "감자랑놀자",
      "body": "안녕하세요 오늘은 멘야마쯔리 신부점 다녀옴 여기는 라멘집임 라멘은 라면과 다른데 여튼 나는 한국에서는 처음먹어봄 내부는 생각보다 아담했음 주방이 제일 컷고 테이블은 7개정도 있었음 2시쯤 갔는데도 꽉차있었음 라멘이 인기가 많은가 아니면 여기가 인기가 많은 맛집인것인가 영업시간 11:00 ~ 21:00 브레이크타임 15:00 ~ 16:30 라스트오더 20:10 여튼 북적북적해서 속으로는 기대했음 주차는 바로옆 공영주차장 이용함 공영주차장이용후 나갈때 차량번호 말하면 주차시간넣어주심 자리에 앉으면 통마늘, 깨, 이런것들이 기본 셋팅 되어있고 물을 주심 바빠보임 주문은 티오더로 하면됨 메뉴 평일 점심 정식(11:00 ~ 15:00) 돈코츠라멘+멘야쇼유규동 13500 카라구찌라멘+멘야쇼유규동 14000 멘야미소라멘+멘야쇼유규동 14000 돈코츠라멘+챠슈차향 13500 카라구찌라멘+챠슈차향 14000 멘야미소라멘+챠슈챠향 14000 돈코츠라멘+볼카츠2pc 14000 카라구찌라멘+볼카츠2pc 14500 멘야미소라멘+볼카츠 2pc 14500 하카타 돈코츠라멘 9000 카라구찌라멘 9500 멘야미소라멘 9500 멘야수제교자 5000 바사삭볼카츠 2pc 5500 4pc 10000 오꼬노미야끼 11000 화산라멘 11000 멘야마제소바 9500 멘야차슈차항 9000 멘야쇼유규동 9000 차슈 3000 아지 타마고 1500 멘마 1500 사리 1500 공기밥 1000 콜라 2000 스프라이트 2000 카스 500ml 5000 우리는 점심특선으로 시켰음ㅜ 다이어트중이라서 배가 맨날고픔 우리는 이렇게시킴 다이어트중인거맞음 그런사람들이이렇게시킴 음식이나옴 다나온건아닌데 어쩌다보니 다나온건 안찍음 배가 그만큼 고팟나봄 볶음밥임 사진보니또 배가고파짐 다이어트의 여파임 ㅜ 다이어트는 왜이렇게힘든건지모르겟음 교자임 교자는 비비고교자만두 그냥 그거같음 라멘은 담백한맛이였음 이건 매콤한맛인데 그냥 기본에 매운맛추가한맛임 그래도 맛자체는 깔끔하고좋았음 볶음밥은... 다아는 볶음밥맛이였음 내가 맛표현을 잘 못하나???? 그냥 볶음밥맛이였음.... 비주얼은 좋았음 뭔가 꽉꽉차보이는게 배부를거같은 느낌이였음 돈까스는 말랑말랑 바삭했음 고기는 그냥 떡갈비?? 고로케??? 같은거에 튀김 씌워논거같았음 교자는....... 위에설명했으니패스 그리고 의자에 보면 의자아래 짐을 보관할수있게해놧음 자리가좁으니 이런식으로 활용할 수 있게해논 센스  통마늘 직접 으깨먹으라고 이거도있음 마늘이 힘겹게나오는거같음 누르는... ",
      "char_count": 1005,
      "image_count": 21,
      "hashtag_count": 0,
      "has_phone": false,
      "has_naver_reservation": false,
      "recency_penalty": false,
      "weight": 1.0,
      "flags": []
    },
    {
      "id": 14,
      "blog_id": "sojin_0928",
      "log_no": "224061627405",
      "url": "https://m.blog.naver.com/sojin_0928/224061627405",
      "date": "2025-11-02",
      "date_raw": "25.11.2.일",
      "title": "2025.10",
      "author": "sojin_0928",
      "body": "이제 개강하고 한 달이 지났다 과제랑 시험에 시달렸다 친구들이랑 다음 수업 가기 전 카페에서 아샷추 마시면서 잠깐 이야기 나눴다 (아샷추 저렇게 꽉 채워서 주셨다..!) 그리고 이날은 교양수업 과제를 하기 위해 미술관에 다녀왔다 평소에 미술관 가는 걸 좋아하지만 과제가 되는 순간 스트레스다 그래도 나름 재밌게 구경했다 이건 다름 작품인데 이곳에 있는 작품은 과제랑 상관없는 거라 그런지 더 재미있었다 ㅋㅋ 전시 다 보고 터미널 근처 카페에 베이글 있는 곳 찾아보고 사러 갔다 이날 추석 때라 본가 내려갈 준비하고 내려갔다 본가에 오자마자 내가 먹고 싶은 거 다 먹었다 : ) 추석 때도 피할 수 없는 과제... 날이 갑자기 추워져서 기모 후드티 꺼냈다 차례 지내러 오랜만에 시골로 갔다 본가만 오면 진짜 엄청 먹는다 (근데 맛있는걸 어떡해..) 피자, 스파게티  이날은 동생이랑 기흥 가는 날! 오랜만에 동생이랑 놀러 가서 신났다 날씨도 너무 좋았고 전철 타고 기흥역까지 갔다 배고파서 서둘러 맘스터치 찾아가는데 길을 한참 헤맸다... 겨우 찾고 맛있게 먹었다 갓 나온 감튀 먹으니 진짜 맛있음! 두 번째 미술관 백남준 아트센터에 왔다 엄청 많은 모니터... 이건 그냥 이뻐서 찍었다 기흥역으로 놀러 간 이유 중 하나, 진격거 프레임! 포토그레이가 있는 곳이 많이 없어서 여기까지 왔다 근처 카페에서 잠깐 쉬어주며 동생이랑 수다 떨었다 이날 너무 재밌게 놀았다 : ) 이 음료는 더 벤티에서 시킨 바닐라딥라떼 진짜 맛있음!! 쿠키도 하나 샀는데 생각보다 크고 맛있었다 이날은 봉사 갔다가 배고파서 라멘집 찾아서 간 곳 근데 맛집을 발견해버림! 진짜 맛있었다 돈코츠 라멘 고기도 너무 맛있고 국물도 진짜 내 취향이었다 저녁에는 떡볶이가 너무 먹고 싶어서 시켰다 꼬치도 하나 먹었는데 역시나 good 이날은 시험 치고 아빠랑 동생이랑 천안에서 놀았던 날이다 전에 먹었던 라멘집 재방문 오꼬노미야끼도 시켰는데 진짜 여기 음식 다 너무 맛있다! ㅠㅠ 가끔씩 생각나면 또 올 듯 근처 가챠샵이 있길래 들렸는데 귀멸의 칼날과 체인소맨 굿즈가 보여 바로 구매했다 너무 행복했던 날 : ) 할로윈 관련 봉사 갔던 날! 부스 운영 봉사였다 귀여운 애기들이 많았다 ㅎㅎ 마제소바 저번에도 왔던 마제소바 집! 초이다이닝에 또 왔다 (난 갔던 곳만 가는 듯...) 영화 보기 전 배부터 채워줬다 다 먹고 팝콘 미리 사서 먹으며 기다렸다 8번 출구 스릴러, 공포2025카와무라 겐키 8번 출구 게임 영상 재밌게 봤던 사람으로서 영화로 어떻게 나왔을지... ",
      "char_count": 920,
      "image_count": 30,
      "hashtag_count": 0,
      "has_phone": false,
      "has_naver_reservation": false,
      "recency_penalty": false,
      "weight": 1.0,
      "flags": []
    },
    {
      "id": 15,
      "blog_id": "krv210329",
      "log_no": "224048105973",
      "url": "https://m.blog.naver.com/krv210329/224048105973",
      "date": "2025-10-21",
      "date_raw": "25.10.21.화",
      "title": "블챌을 가장한 일상글 투척",
      "author": "이청",
      "body": "요즘 뭐랄까.. 특별히 하는 것이 없다.. 집에서 고뇌하기.. 고민하기.. 걱정하기 등.. 뭐 이런거나 하고 있다. 그래도 삶을 살고는 있으니 !!! 간단한 일상 글을 써본다. 그리고 !! 지금 시험기간이라 블챌.. 마땅히 할 것이 없다. 돈도 없고 시간도 없고 놀러갈 곳도 없고 마음의 여유도 없다고 !!! 그러니까 이번엔 일상글로 .. 대체하겠다. (일상글이라기보단.. 뭐 먹었는지 .. 적은듯) 교촌 순살 레드허니 반반이랑 엽떡. 이거 두 개를 얼마에 먹었는지 아십니까? 8000원이라는 말도 안되는 가격에 먹었다. 치킨은.. 예전에 지역경제 혁신 박람회 이벤트 응모했다가 받은 기프티콘 사용.. 참고로 이거 받았음. 매장가서 기프티콘 보여주고 메뉴 바꿨다. 간장한마리+콜라1.25L 엽떡도 4000원에 주문했다. 예전에 보이즈플래닛 2인가 그거 할 때 파이널투표 선착순 만명 이벤트에서 당첨되어서.. 나랑 친구랑 둘 다 당첨되어서 각 5000원씩 배민 쿠폰을 받았기 때문에 엄청 합리적인 가격에 먹을 수 있었다. 진짜 맛있었는데..... 엽떡이 한 통에 14000원.... 엽떡 한 통이 내 시급을 넘는다는 얘기를 하다가 현타왔었다 ㅋㅋ 언제인지는 정확하게 기억이 안나는데 분식집에서.. 친구랑 둘이 거하게 먹었다. 떡볶이랑 어묵, 돈가쓰 김밥.. 다 해서 만원이 넘지 않았던 것 같다. 돈까스도 막 튀겨서 넣어주시니 뜨끈하고 끝내주게 맛있었다. 케찹맛이 나는 떡볶이.. 오랜만 ! 너무 음식 사진만 있는 것 같은데.. 그렇게 됐다. 어디를 다녀온 글들은 다 따로 빼서 쓰기 때문에..... 그걸 제외한 나머지 일상을 추리면 뭘 먹음. 이런 것밖에 없다. 아무튼 멘야마쯔리 화산라면 끝내주게 맛있다. 날이 제법 추워졌다.. 사실 이 붕어빵 먹을 때에는........ 그리 춥진 않았다. 그래도 벌써 붕어빵 장사를 개시하는구나.. 근데.. 붕어빵 가격 실화인가요. 아니 붕어 3마리에 2000원이라니..... 왤케 비싸.... 진짜 말도 안됨. 라떼는 3마리 1000원이었는데.. 요즘 그러면 인건비도 안나오겠지.. 뭐 이것도 참 맛있었다. 갓 구운 것처럼 말도안되게 뜨끈뜨끈해서.. 용암같았음. 아니 그리고 다이소 구경갔는데.... 누가 FUCK를 만들고 도망갔나봄.. 저기서 3m도 떨어지지 않은 곳에 카운터가 있는데 ... 참 비범한 놈일세. 내 사랑 오피스토이몰. 체인소맨 쿠지가 입고되었다고해서 달려갔는데. 품절이란다. 아니근데 오피스토이몰 한 2년전만해도 나만 아는 가게 느낌이었는데... 요즘은 사람도 넘 많이 오고.. 장사도 제법 잘되는 것 같고.... 내가 가면 이제 갖고 싶은 물건도 없고 ....... ",
      "char_count": 1005,
      "image_count": 21,
      "hashtag_count": 0,
      "has_phone": false,
      "has_naver_reservation": false,
      "recency_penalty": false,
      "weight": 1.0,
      "flags": []
    },
    {
      "id": 16,
      "blog_id": "cloud0420",
      "log_no": "224002155150",
      "url": "https://m.blog.naver.com/cloud0420/224002155150",
      "date": "2025-09-10",
      "date_raw": "25.9.10.수",
      "title": "[일본식라면] 멘야마쯔리_신부점",
      "author": "승짱",
      "body": "[멘야쯔리] 돈코츠 규동 세트 ⭐⭐⭐⭐ ○ 주소 : 충남 천안시 동남구 신부동 454-1 ○ 영업시간 : 화-일 (11:00 ~ 21:00) ○ 브레이크타임 : 15:00 ~ 16:30 ○ 라스트 오더 : 20:10 ○ 휴일 : 매주 월요일 ○ 주차 : 건물 유료주차장 OR 신부 제5공영주차장 (유료) ○ 연락처 : 0507-1381-6907 안녕 이친이들, 외식인생 36년차 승짱이야  오늘은 청안에서 먹어보게된 라멘체인점 매장 #멘야마쯔리 소개할게  멘야마쯔리 신부점은 먹자골목에 위치해 있어서 네비 찍고 가는 데는 전혀 어려움이 없었어. 다만 주차장 때문에 세 번 정도 헤맸어  매장 좌측에 별도 주차장이 있긴 한데, 공간이 협소하고 선불 4,000원을 내야 해서 불편했어. 그래서 나는 매장에서 도보로 5분도 안 걸리는 공영주차장을 추천해! ️ 주차장 정보 위치 : 신부동 제5공영주차장 주소 : 천안시 동남구 먹거리11길 12 연락처 : 041-529-5120 주차 공간 : 1층~7층 + 옥상까지 주차 가능 금액 : 최초 30분 무료 / 이후 10분당 200원 2시간 초과 시 10분당 300원 / 1일 주차권 10,000원 특이사항 : 10월 12일(일)까지 무료 운영 중 나는 평일 낮에 방문했는데, 5층까지 만차라 결국 6층에 주차했어. 그래도 엘리베이터가 있어서 이용하는 데 전혀 불편함은 없었어! 매장 내부는 전체적으로 아담한 편이었어. 소규모 손님들이 주로 와서 그런지 테이블 간격이 다소 좁고, 테이블 아래 공간도 협소해서 조금 불편했어. 그렇지만 또 이런 분위기가 일본식 라멘집 특유의 감성 같아서 나쁘지 않게 느껴지더라 화장실은 매장 뒷문을 통해 외부로 나가서 별도 건물로 들어가야 이용할 수 있었어. 남녀 구분이 잘 되어 있었고, 내부도 꽤 깨끗했어 다만 비밀번호가 따로 필요해서, 뒷문에 적힌 번호를 꼭 확인하고 가야 해! 메뉴는 라멘, 소바, 볶음밥, 규동, 볼카츠까지 다양했어. 사이드로는 교자랑 오꼬노미야끼도 즐길 수 있었어 특히 평일 점심에는 세트 메뉴를 할인된 가격으로 먹을 수 있으니까 참고해! 테이블에는 기본으로 마늘, 후추, 참깨, 생강이 셋팅되어 있었어. 특이하게도 생마늘이 기본 제공되더라! 취향에 따라 테이블 서랍에 있는 마늘 다지기로 직접 다져서 라멘에 넣어 먹으면 훨씬 맛있다고 하더라고 나는 평일 낮에 방문해서 런치 세트를 이용했어 그중에서 돈코츠라멘 + 규동 세트를 주문했어! 돈코츠라멘은 국물이 진하고 깊은 맛이 났어 차슈도 3개 정도 올라가 있었고, 반숙 계란이 특히 맛있더라! 근데 반쯤 먹고 나니 특유의 느끼함 때문에 조금 물렸어. 지금 블로그... ",
      "char_count": 973,
      "image_count": 31,
      "hashtag_count": 1,
      "has_phone": true,
      "has_naver_reservation": false,
      "recency_penalty": false,
      "weight": 1.0,
      "flags": []
    },
    {
      "id": 17,
      "blog_id": "ppo10000",
      "log_no": "223996525716",
      "url": "https://m.blog.naver.com/ppo10000/223996525716",
      "date": "2025-09-06",
      "date_raw": "25.9.6.토",
      "title": "멘야마쯔리 신부점 [ 천안 동남구 신부동 맛집 ]",
      "author": "격스트",
      "body": "멘야마쯔리 신부점 안녕하세요 격스트 김석훈입니다. 천안 동남구 신부동 에 위치한 멘야마쯔리 신부점 에 다녀왔습니다. 일본 라멘을 먹을 수 있는 이곳은 어땠는지 지금 알려드리겠습니다. 멘야마쯔리 메뉴 멘야마쯔리 신부점 오픈시간 이곳은 입구부터 올드한 느낌이었습니다. 오픈시간을 꼭 확인하고 들려주세요. 이날은 비가 오는 날이었습니다. 멘야마쯔리 키오스크 멘야마쯔리 밑반찬 테이블마다 주문이 가능해 편했습니다. 오픈주방으로 음식조리과정도 볼 수 있었습니다. 라멘을 시키고 내부를 감상했습니다. 가격은 적당한 가격이었습니다. 멘야마쯔리 신부점 내부인테리어 돈코츠 미소라멘 진한 국물과 차슈,계란까지 완벽했습니다. 좋은 맛으로 또 방문하고 싶은 라멘이었습니다. 한번은 들려서 드셔보세요. 솜씨가 중요하다 -격스트- #멘야마쯔리 #멘야마쯔리신부점 #천안맛집 #신부동맛집 #천안라멘 #신부동라멘",
      "char_count": 352,
      "image_count": 7,
      "hashtag_count": 6,
      "has_phone": false,
      "has_naver_reservation": false,
      "recency_penalty": false,
      "weight": 1.0,
      "flags": []
    },
    {
      "id": 18,
      "blog_id": "elwlsl123",
      "log_no": "223992510649",
      "url": "https://m.blog.naver.com/elwlsl123/223992510649",
      "date": "2025-09-02",
      "date_raw": "25.9.2.화",
      "title": "펫시터가 된 날 (근데 이제 우리집 가나디인...)",
      "author": "여나",
      "body": "가족여행을 떠난 엄빠와 동생 대신 집에 있을 가나디를 돌봐주기 위해 상경하는 나 가기전에 인스타에서 본 오레오 아이스크림을 해먹고 싶어서 굳이 마트에 들러서 사왔는데 아직도 안먹었슨... 갑자기 먹기 싫어졌슨.. 친구가 선물해 준 비즈 꽃 반지.... 외출할때만 끼는 아끼던거였는데.. 화장실 갔다가 손씻는데 뭐가 떠내려가길래 ? 하고 봤더니 내 반지였슨... 진짜 어이없게 뭐 박박 씻은것도 아니고 진짜.. 의식도 못하는 사이에 떠내려가서 비즈 두개만 사진 찍어둠.. 내 반지 ㅠ^ㅠ 점심은 뭐먹을까 오지게 고민한 끝에 신부동 멘야마쯔리! 예~~~전에 갔을 때 돈코츠 라멘을 먹었는데 계란을 그냥 냅다 완숙으로 줘서 그 뒤로 한번도 안갔는데 마제소바가 땡겨서 다시 방문했다! 개인적으로 라멘의 계란은 무조건무조건무조건 촉촉한 반숙란(aka 감동란) 이 근본이라는 생각에 아무리 맛있어도 계란이 완숙으로 나오는 곳은 가지 않는다. 나의 개똥철학 ㅎㅎ 이번에는 음식은 참 맘에 들었는데 응대가 차암 맘에 아쉬웠다^^... 자리마다 티오더가 있어서 주문했는데 조금 뒤에 와서 기계를 껐다 켜는 사이에 주문을 해서 주문이 안들어갔다면서 다시 주문해달라고 해서 주문을 다시 넣었다 근데 또 조금 뒤에 오더니 계속 주문이 안들어왔다고 하면서 뭘 주문했는지 물어보고 우리 주문내역도 한참 보면서 폰으로 뭘 적더니 가시길래 주문을 받아간 줄 알았다 또 또 10분쯤 뒤에 오더니 주문이 안들어갔다고 다시 주문을 해달라고;;; 이게 자리에 앉고 거의 20분이 지난 시간동안의 일... 주문이 그렇게 안들어갔으면 수기로 받아갔으면 됐을 일이고, 중간에 와서 메뉴는 왜 물어봤던걸까 싶었다 (복잡하게 주문한것도 아니고 마제소바랑 돈코츠라멘 하나씩만 주문함..) 안되는걸 인지했으면 처음부터 수기로 받아서 주문해줬으면 좋았겠다 싶었는데 주문이 들어가니까 메뉴는 금방 나와서 걍 얼른 먹고 나왔는데.. 좀 더 유연하게 대처해줬으면 좋았겠다 싶었음 ㅠ 잘 먹고 인형뽑기까지 둘러보고 집와서 가나디와 잠깐 휴식타임 ㅎㅎ 얘네는 갑자기 엄마 아빠가 왜 집에 안왔는지도 모르겠는데 큰누나가 갑자기 왜 집에 왔는지도 모를일이지만 마냥 신났더랬다 ㅋㅋㅋ 조금 쉬다가 집에서만 놀아주기는 아쉬우니까 해가 살짝 넘어갈 때 카페에 갔다! 애견동반카페인데 운동장이 작게 있어서 그런건지 완전 애견카페는 아니여서 그런건지 입장료를 안받고 신상카페라해서 가봤다! 집에서는 약 15분정도 걸리는 가까운 곳이였고, 화덕 피자도 파는... ",
      "char_count": 939,
      "image_count": 42,
      "hashtag_count": 0,
      "has_phone": false,
      "has_naver_reservation": false,
      "recency_penalty": false,
      "weight": 1.0,
      "flags": []
    },
    {
      "id": 19,
      "blog_id": "daisuki1980",
      "log_no": "223976637691",
      "url": "https://m.blog.naver.com/daisuki1980/223976637691",
      "date": "2025-08-20",
      "date_raw": "25.8.20.수",
      "title": "쉬는날 또 댕겨옴,,,, + @",
      "author": "쉼",
      "body": "요즘 볼일이 생겨서 부쩍 자주 가는 천안  또 다녀왔습니다  자주 가서 그렇게 느끼는건지 모르겠지만 서울하고도 가깝고 천안.. 참 매력적인곳임에 틀림없다!! 가는 도중 구름이 너무 예뻐서  터미널 근처 찾아낸 맛집  \"멘야마쯔리\" 이번이 두번째 방문입니다  가자마자 탄산 한 번 쭈욱 들이키구요  근데 스프라이트보다는 저 시원해보이는 저 차(tea)가 더 맛있었던건 안 비밀  오늘은 잔뜩 먹고 배 빵빵하게 채우려고 셋뚜 메뉴 시킴 ☺️ “톤코츠 라아멘 + 챠슈챠항 셋또“ 메뉴 역시 라멘은... 육수와 챠슈와 반숙계란인겨  요 세개의 조화가 잘 되어야 맛이 보장 되는거지 ☺️ 그래서 음총 맛나게 잘 묵었습니당  교자도 좋아하는데 겉바속촉 역시 쵝오  글구 그동안 나 몰랐는데 라멘에 토핑 된 콩나물?? 숙주?? 아삭한게 왤케 식감도 좋고 맛나냐  이렇게 메뉴 세개 잘 비우고 배 든든하게 잘 채우고 갑니당  앗!! 그리고 개인적으로.. 여기가 좋은 이유 또 하나!! 가게 내 음악이 일본 노래만 나오는데 그것도 한참 내가 J-pop에 미쳐있던 시절의 제이팝만 엄선해서 나와서 좋았음  나카시마 미카 니시노카나 히라이켄 엑스재팬... 글구 어제는.... 라르크엔시엘 L'Arc ~ en ~ Ciel ”Honey\"가 흘러나와 속으로 막 따라 불렀음  혼자 추억에 빠지며 완전 씐났음 씐났음  그렇게 멘야마쯔리를 나서고 시간이 많이 남아... 천안이 맛있는 빵집이나 베이커리 가게가 많다고 하여 멘야마쯔리 주변에 “브루어스” 라는 구운 과자 전문점에 가봄 카운터에서 주문하면 저 번호를 보고 직원분들이 주문한것을 테이블에 가져다주는 방식이다.. 여담 - 10번 자리 너무 뻘쭘해서 벽쪽 6번 자리로 옮김  인테리어 너무 마음에 들고..❣️❣️❣️ 그렇게 배 터지게 먹고도 후식 들어갈 배는 또 따로 있는 법  아이스아메리카노랑 카라멜솔티드 휘낭시에 + 바닐라 까눌레 시킴  한 입거리ㅋㅋㅋㅋㅋㅋ 단짠단짠 조화가 좋은 카라멜솔티드 휘낭시에가 특히 너무 맛있었다  인테리어 예쁨  좌 아이폰 16 & 우 갤럭시 S25 이렇게 보니깐 또 아이폰 색감이 마음에 드는건 왜 때문인지.. 그렇게 나는 바리바리 싸들고 이제 커피숍을 나섭니다 그래.. 인생은 혼자야... 다 필요없고 혼자 잘 먹고 잘 살면 되는거지 그렇게 나는.. 혼자 여유부리고 힐링하며 이제 서울로  그래도 천안하면 기승전 학화호도과자  호도과자 깨알같이 하나 사들고 갑니당 ♀️♀️♀️ 오늘아침.. 출근전 시간 떼우며 스벅에서 아라랑 냠냠  그리고 ⬇️⬇️⬇️ 요즘 매일 물 많이... ",
      "char_count": 932,
      "image_count": 24,
      "hashtag_count": 0,
      "has_phone": false,
      "has_naver_reservation": false,
      "recency_penalty": false,
      "weight": 1.0,
      "flags": []
    },
    {
      "id": 20,
      "blog_id": "waiuflk",
      "log_no": "223975818191",
      "url": "https://m.blog.naver.com/waiuflk/223975818191",
      "date": "2025-08-19",
      "date_raw": "25.8.19.화",
      "title": "[천안] 일본라멘 전문점~ \"멘야마쯔리 신부점\" (내돈내산, 후기)",
      "author": "최소소",
      "body": "안녕하소소~! 천안신부동 먹자골목에 위치한 일본라멘집 멘야마쯔리에 소소가 방문했소 \"멘야마쯔리 신부점\" 영업정보 위치, 전화번호, 영업시간, 주차, 화장실 천안 터미널 맞은편 신부동 먹자골목 안에 위치해 있어요~ 아홉가지 약속치과 뒤쪽에 있어요~ [멘야마쯔리 신부점] 충청남도 천안시 동남구 만남로 18 휴먼빌딩 1층 ☎ 0507-1381-6907 오전 11시 ~ 저녁 9시 (라스트 오더 저녁 8시 10분) 브레이크 타임 3시 ~ 4시 30분 매주 월요일 정기휴무 주차 X/ 내부화장실 X 민생지원금 O 소소의 주차장 점수 : ☆☆☆☆☆ (소시지 빵점) 주차장 따로 없어서 소소는 신세계 백화점에 주차를 했어요 (신세계 지하 1층 이마트에서 시장 보고 영수증으로 주차 정산 했어요) 꿀팁 (이건 첫번째 레슨!) 런치 타임 이벤트, SNS 리뷰 이벤트 점심 11시 ~ 15시에 방문하면 라멘 무료 사이즈업! 여기서 끝이 아니죠~! 네이버 또는 SNS 리뷰 작성하면 음료수, 아지타마고(계란) 차슈 3p 중에 1개 무료제공 알뜰 소소는 모든 혜택을 챙겼소소 작지만 귀여운 일본라멘집 내부, 메뉴 오픈 주방으로 되어 있어요~ 22명 정도 착석 가능한 내부에요~ (넓지 않아 웨이팅 있을 수 있어요) 소소와 서방은 돈코츠 라멘(무료 사이즈업) 9,500원 카라구찌 라멘(매운 라멘) (무료 사이즈업, 2단계 매운맛) 10,000원 주문했어요~ 양 많은 라멘 음식 사이즈업이라서 그런지 양이 어마어마해요 안에 계란이랑 차슈랑 숙주도 들어있어요 매운라멘 2단계는 입이 얼얼할 정도로 매운맛이에요 여기 식당의 대표메뉴인 돈코츠 라멘은 고소하고 담백했어요 소소의 맛평가 : ★★☆☆☆ 한국인 소소는 일본 라멘보다는 집에서 먹는 열라면이 더 맛있어요 내돈내산 \"멘야마쯔리 신부점\" 에 대한 소소의 한줄평은? ★★☆☆☆ 일본 라멘 좋아하시는 분들 추천해요! 천안 신부동 먹자골목에 오랜 자리를 지키고 있는 라멘집 근처 공용 주차장이나 신세계 백화점 주차장에 주차하셔야 해요!",
      "char_count": 755,
      "image_count": 12,
      "hashtag_count": 0,
      "has_phone": true,
      "has_naver_reservation": false,
      "recency_penalty": false,
      "weight": 1.0,
      "flags": []
    },
    {
      "id": 21,
      "blog_id": "0v0_77",
      "log_no": "223936863086",
      "url": "https://m.blog.naver.com/0v0_77/223936863086",
      "date": "2025-07-17",
      "date_raw": "25.7.17.목",
      "title": "[천안 동남구 신부동] 멘야마쯔리 카라구찌 라멘, 볼카츠 솔직후기",
      "author": "꼼뮤",
      "body": "멘야마쯔리 • 천안 동남구 신부동 454-1 • 11:00 - 21:00 (15:00 - 16:30 브레이크 타임) • 매주 월요일 정기휴무 • 0507-1381-6907 • 포장, 배달 가능 오픈 시간 맞춰서 방문했다 솔직히 맛있다는 후기가 많아서 기대가 컸음 전 날 술 많이 마셔서 카라구찌 라멘 3단계로 주문함 근데 솔직히 내가 생각한 비주얼이 아니라서 놀랐다 아침이지만 라멘에 맥주 빠지면 섭섭하니까 카스도 하나 주문했다 면이 얇고 양이 많음 근데 숙주 양이 적어서 좀 아쉬웠다 차슈는 .. 음 .. 이런 차슈 처음 봐서 매우 당혹스럽달까 사이드로 볼카츠도 추가함 막 엄청 맛있다! 꼭 먹어야 해! 하는 맛은 아님 그냥 배고프면 드세요",
      "char_count": 266,
      "image_count": 8,
      "hashtag_count": 0,
      "has_phone": true,
      "has_naver_reservation": false,
      "recency_penalty": false,
      "weight": 1.0,
      "flags": [
        "extraction_warning:266자"
      ]
    },
    {
      "id": 22,
      "blog_id": "midoridiary",
      "log_no": "223930561757",
      "url": "https://m.blog.naver.com/midoridiary/223930561757",
      "date": "2025-07-12",
      "date_raw": "25.7.12.토",
      "title": "천안 신부동 라멘 맛집, 멘야마쯔리 내돈내산",
      "author": "미도리",
      "body": "천안 신부동 라멘 맛집 멘야마쯔리 11:00-21:00 브레이크타임 15:00-16:30 매주 월요일 정기휴무 0507-1381-6907 나 어때? 오늘 쫌 멋져? 우리 내일 제주도로 떠난당!!! 기념으로 우리 그이 썬글라스 하나 뽑아줌 집가자마자 스피드하게 짐싸야 되니까 술은 자제하고 최대한 소주 안땡기는 메뉴로 골라봄 오랜만에 라멘 가자ㅑ 추억의 맛집 멘야마쯔리,,, 소싯적에 쌍용점에 빠져 한참 다니다가 신부점에서 실망한 뒤로 또 한참 안가고 이번이 몇년만에 재방문이다 멘야마쯔리 내부 사람이 많아서 내부 사진을 제대로 못찍었는데 대략 6-7석 정도의 아담한 규모다 깔끔한 오픈형 키친임 멘야마쯔리 메뉴 돈코츠라멘 9,500원 카라구찌라멘 2단계 10,000원 *2단계: 신라면 2-3배 맵기 (3단계까지있음) 교자 5,500원 주문 땅땅 ! 사실 오늘 멘야마쯔리에 온 이유는 아사히 쌩맥때문이라고 해도 과언이 아니었는데 왜 더 안내려가여 왜 아사히 쌩맥 없어여 광광 ㅠㅜㅜㅜㅜ 아쉬운대로 카스라도 주문해봤지만 싱거운 카스로는 아쉬움이 채워지지 않았다^.ㅠ 일식은 나마비루랑 페어링해야 제맛인것을 돈코츠라멘 우리 그이 픽 돈코츠육수가 너무 연하지도 진하지도 않은 적당함이라 부담없이 먹기 좋은 맛이라고 함 그리고 멘야마쯔리 오면 꼭 시키던 교자 요게 겉바속촉에 간도 짭짤해서 맥주 안주로 그만임 아사히 쌩맥의 부재가 한번 더 사무침^^ (ㅋㅋㅋㅋㅋㅋㅋㅋㅋ질척) 카라구치 라멘(2단계) 나의 원픽 카라구치 푹푹 고은 육수에 매운맛이 더해지니 꽤 자극적임 혓바닥이 따가워지는 캡사이신의 매움이었는데 육수가 내추럴해서 인공적인 매움이 더 나은 방향으로 보정되는 느낌이었다 다음엔 걍 1단계 먹을듯ㅋ 반숙란은 반갈해서 먹으면 입에 넣자마자 실종돼불고 차슈에 싸먹으면 돼지향이 한겹 더 삭 감싸는것이 풍미 업ㅋ 예전에 왔을땐 짜기만해서 맛없었는뎈ㅋㅋ 오늘은 간도 좋고 면 익힘정도도 좋고 호로록호로록 연신 들어가더라는 마지막 한입은 japanese 만두국 느낌으로 설거지^^~~~~~~~ 혼밥하기 좋고 직원들도 친절하고 라멘도 맛있음 개인적으로 맥주 안주가 그렇게 많은데 아사히 쌩맥이 없다는게 두고두고 아쉬운ㅋㅋㅋㅋ 천안 신부동 멘야마쯔리 추천추천 !",
      "char_count": 852,
      "image_count": 22,
      "hashtag_count": 0,
      "has_phone": true,
      "has_naver_reservation": false,
      "recency_penalty": false,
      "weight": 1.0,
      "flags": []
    },
    {
      "id": 23,
      "blog_id": "solascriptura1",
      "log_no": "223923268464",
      "url": "https://m.blog.naver.com/solascriptura1/223923268464",
      "date": "2025-07-07",
      "date_raw": "25.7.7.월",
      "title": "천안 숨은 맛집 발견! 멘야쯔리 화산라멘이 입맛을 완전히 사로잡았다",
      "author": "solascriptura1",
      "body": "천안 터미널 근처 일본식 라멘 맛집 멘야쯔리 안녕하세요! 충남 곳곳의 숨은 맛집을 발굴하고 있는 저에게 또 하나의 보물 같은 곳이 생겼습니다. 바로 천안 터미널 근처에 위치한 일본식 라멘 전문점 멘야쯔리입니다. 평소 라멘을 좋아하는 편이지만, 이곳의 대표메뉴인 화산라멘을 먹고 나서는 정말 충격을 받았습니다. 지금까지 먹어본 라멘과는 완전히 다른 차원의 맛이었거든요!  화산라멘, 그 이름에 숨겨진 비밀 화산라멘이라는 이름부터 호기심을 자극하지 않나요? 실제로 먹어보니 그 이름이 결코 과장이 아니었습니다. 마치 화산이 폭발하듯 입안에서 터지는 깊고 진한 맛의 향연이 펼쳐졌습니다. 국물은 진짜 예술입니다. 첫 숟가락부터 마지막 한 방울까지, 계속해서 새로운 맛의 층위를 발견할 수 있었어요. 깊은 감칠맛과 함께 은은한 매운맛이 조화롭게 어우러져 있어서, 한 번 먹기 시작하면 정말 멈출 수가 없더라구요.  완벽한 조화의 미학 면발도 정말 인상적이었습니다. 쫄깃하면서도 부드러운 식감이 화산라멘의 진한 국물과 완벽하게 어우러져 있어요. 면을 한 젓가락 들어 올릴 때마다 국물이 적당히 묻어나오면서 입안에서 환상적인 하모니를 만들어냅니다. 토핑 하나하나도 세심하게 준비되어 있어서, 그냥 장식이 아니라 화산라멘 전체 맛의 핵심 역할을 하고 있더라구요. 모든 재료가 하나의 완성된 작품을 만들어내는 것 같았습니다.  접근성 좋은 위치의 숨은 보석 천안 터미널 근처에 위치해 있어서 대중교통으로 접근하기도 정말 편리합니다. 출장이나 여행 중에도 쉽게 들를 수 있는 위치죠. 하지만 위치가 좋다고 해서 맛까지 평범한 건 절대 아니에요! 식당 내부 분위기도 정말 아늑하고 편안합니다. 일본 현지 라멘집에 온 것 같은 느낌이 들어서, 음식뿐만 아니라 분위기까지 완벽하게 즐길 수 있어요.  왜 멘야쯔리 화산라멘인가? 솔직히 말씀드리면, 충남 지역에서 PR 업무를 하면서 정말 많은 맛집을 다녀봤습니다. 하지만 멘야쯔리의 화산라멘은 정말 특별했어요. 단순히 맛있는 수준을 넘어서서, 먹고 나서도 계속 생각나는 그런 맛이었거든요. 이런 훌륭한 맛집이 충남에 있다는 사실이 정말 자랑스럽습니다. 지역 경제 활성화는 물론이고, 천안을 찾는 분들에게 특별한 경험을 선사할 수 있는 곳이라고 확신합니다.  강력 추천하는 이유 화산라멘 하나만으로도 충분히 만족스럽지만, 멘야쯔리는 그 이상의 가치를 제공합니다: 첫째, 완전히 새로운 맛의 경험을 할 수 있습니다. 기존에 알던 라멘의 고정관념을 완전히... ",
      "char_count": 931,
      "image_count": 2,
      "hashtag_count": 0,
      "has_phone": false,
      "has_naver_reservation": false,
      "recency_penalty": false,
      "weight": 1.0,
      "flags": []
    },
    {
      "id": 24,
      "blog_id": "ekshin20",
      "log_no": "223844698727",
      "url": "https://m.blog.naver.com/ekshin20/223844698727",
      "date": "2025-04-24",
      "date_raw": "25.4.24.목",
      "title": "[천안맛집] 신부동 라멘 맛집인 멘야마쯔리 내돈내산 솔직후기/영업시간,메뉴판,매운라멘단계",
      "author": "갱이",
      "body": "안녕하세요! 오늘은 천안 신부동에 위치한 멘야마쯔리 후기입니다:) 영업시간 : 화~일 : 11:00~21:00 브레이크타임 : 15:00~16:30 전화번호 : 0507-1381-6907 주소 : 충남 천안시 동남구 만남로 18 평일에는 사이즈업 이벤트도 하시는 것 같아요 저는 토요일 2시 30분정도에 방문해서 그런건지 웨이팅은 따로 없었어요 메뉴판 저는 얼큰한 라멘을 좋아해서 화산라멘이랑 카라구찌라멘 중 고민했는데 다른 리뷰를 보니 화산라멘은 걸쭉하다고 하다고 해서 하카타 돈코츠라멘(10,000원)과 카라구찌라멘(10,000원) 2단계로 주문했어요! (지금 보니 인터넷에 있는 가격에서 조금 오른듯해요) 테이블은 6~7개정도 있어요 마늘 갈아먹을 수 있게 구비되어있는데 통에 들어가있는게 조금 더 위생적이지 않을까 생각들었어요 마늘이 말라있슴요 ,, (불편러 아니에여ㅠ) 반찬도 따로 없는데 저 생강? 으로 만든게 있더라구요 전 매콤한거 시켜서 단무지 있냐고 여쭤봤는데 김치만 있다고하셨어요 나왔습니다 ㅎ.ㅎ 리뷰이벤트로 받은 챠슈(3P)예요 계란은 통으로 하나가 들어가서 좋더라구용 마지막 공기밥 추가(1,000)까지 해서 야무지게 먹었네요 저는 개인적으로 코이라멘이 더 맛났던 것 같아용 .. (다음에 리뷰예정) 안뇽 ..",
      "char_count": 503,
      "image_count": 17,
      "hashtag_count": 0,
      "has_phone": true,
      "has_naver_reservation": false,
      "recency_penalty": false,
      "weight": 1.0,
      "flags": []
    },
    {
      "id": 25,
      "blog_id": "phoenix2514",
      "log_no": "223838652782",
      "url": "https://m.blog.naver.com/phoenix2514/223838652782",
      "date": "2025-04-18",
      "date_raw": "25.4.18.금",
      "title": "천안 신부동 멘야마쯔리 라멘맛집 냠냠챱챱",
      "author": "가니가니",
      "body": "신부동 맛집 멘야마쯔리 멘야마쯔리...! 굉장히 유명한 라멘맛집이죠! 저도 워낙 명성이 자자하다보니 이름은 익히 알고 있었고 쌍용동에 있는 멘야마쯔리가 한국판 미슐랭이라는 블루리본(?)에 선정되기도 하고 엄청 유명하다고는 들었는데 오늘은 거기 말고 그냥 신부동 데이트 하다가 신부동 멘야마쯔리 방문한 후기를 공유드려용 찾아오시는 길 휴무날 저희 부부는 신부동으로 데이트를 하러왔습니다~~~ 정말 신부동은 천안 최고의 핫플이라고 생각해요~ 사람도 많고 신세계 백화점도 잘되어있고!^^ 히히 여기저기 둘러보고 신부동에 핫한 거리를 걷다가 멘야마쯔리라는 라멘집을 발견해서 배도 채울겸 방문해보았습니다 오 겉에서 풍기는 분위기가 좀 대단하네요 근데 제가 고딩때만 해도 옛날에는 일본과 똑같은 맛을 재현한 라멘집이 있다고 하면 사람들이 난리가 나서 다 몰리고 그랬는데 요즘은 워낙 일본풍의 라멘집이 많이 생기고 많이 접해봐서 그냥 음 맛이 괜찮겠는데? 정도네욬ㅋㅋㅋㅋㅋㅋㅋㅋ좀 안타까워용...그나저나 나 고딩대면 벌써 20년이....지난ㅇ... 각설하고, 확실히 일본라멘집다운 분위기는 뿜뿜합니다 어서 문을 열고 들어가볼게용 딱 일본라멘집 스타일의 내부 분위기였어요 직원분들께서 아주 반갑게 맞이해주시네용 3번 테이블에 앉으면 된다고 하셔서 착석했습니다 마실 물은 테이블 정중앙에 놓여있었고, 컵,국그릇(?),마늘 등이 있습니다 그리고 옆 테이블 서랍에는 숟가락,젓가랏, 티슈랑 그 마늘 으깨는 도구가 있으니 참고해주세용 저 마늘은 라멘을 그냥 먹었을때의 맛이랑 마늘 하나 으깨서 넣은 맛이랑 확연히 차이나는데... 고객님들께서도 한번 차이를 느껴보시고 이후에는 취향에 맞게 즐기시면 될것같아용 태블릿으로 주문하는 시스템이예요 저는 카라구찌라멘+볼카츠 2pc (14,500원) 와이프님은 멘야미소라멘 (10,000원)을 주문했습니다 화장실은 이쪽으로 나가셔서 바로 앞건물로 가시면 되용 와이프님의 멘야미소라멘이예요 한입 드셔보시고는 바로 극찬을 날리시네요 제 카라구찌라멘이 나왔습니다 맵기가 신라면 정도로 하고 계란 추가했었나? 암튼 생각없이 막 추가 했습니다 비쥬얼이 좋네욬ㅋㅋㅋㅋㅋㅋ 국물맛도 끝내주고요 일본느김 한가득이예요 신라면이나 오징어짬뽕과는 다른 결의 맛 매력있습니다 볼카츠도 나오는데 레몬즙도 따라 나올길래 쭉 짜서 방울 방울 떨어트려줬어용 요곤 영수증 리뷰 쓰면 주신다고 하셔서 정성스레 작성하고 차슈 3pc 얻었습니다 반숙이 기가맥히네요 넘... ",
      "char_count": 954,
      "image_count": 17,
      "hashtag_count": 0,
      "has_phone": false,
      "has_naver_reservation": false,
      "recency_penalty": false,
      "weight": 1.0,
      "flags": []
    },
    {
      "id": 26,
      "blog_id": "weriut542",
      "log_no": "223823092179",
      "url": "https://m.blog.naver.com/weriut542/223823092179",
      "date": "2025-04-06",
      "date_raw": "25.4.6.일",
      "title": "천안 라멘 멘야마쯔리",
      "author": "감미경",
      "body": "으악 저때가 ... 두달전인가 호호호호 ㅋㅋㅋㅋㅋㅋ ㅋㅋㅋㅋㅋㅋㅋ 근데 이제서야 적는 이U 는 .. 이제 저장이 안된다기에 우우우우ㅜ우 ~~ ㅋㅋㅋㅋㅋㅋㅋㅋㅋ ㅋㅋㅋ ㅋㅋㅋㅋㅋ 아니 집 앞에서 이상한 걸 받아오신 떠돌이 수정시 ,,, 거절할 줄 좀 알아봐 ,, 근데 아학 ... ㄴ나학 ... 하면서 아프다고 다리를 걷어제끼기 시작하심 근데 다리를 보니까 ㅋㅋㅋ 나이가 맻갠디 .. 아직도 넘어지냐 니는 ㅜ ㅜ 진짜 서서 바로 무릎들이 땅바닥에 기도했다는거임 고정도면 ,,, 유교적인 .. 정신인거 아니가 .. 요즘엔 안넘어지제 ..? 안 춥냐고 물어보니까 ㅅㅂ ㅋㅋ'=' 말도 말라고함 아 이 표정 사악 지어지면서 나가기 싫어지는데 이미 집에 데리러 오셨는데 나가줘야 함 안나가면 쥐질지도 모름 양 사이드에서 싸우고 있는 사오정들 ,, 나 좀 ㅅㅏㄹ려달라 그래서 결ㄹ국엔 나와찌 모 ~ 터미널 쪽에서 내려가지고 구경을 해주는데 아니 천안은 회전목마 말이 여기저기 버려져 있냐 ?? 뭔 일 있었던 거 아님 ??? ???? 두정동 술집 거리에도 흰색말 있음 .... 다 합치면 회전목마 하나 만들 수 있는 거 아니가 오른쪽 사진은 키작녀 옷 집인 거 같음 괜찮아보여서 킵해뒀는데 ㅋㅋㅋㅋ 그냥 집에 와버렸지 모임 인형뽑기 집에 왔는데 전날 저녁에 릴스에서 본 키위 인형이 있는거임 ??? 뒤집으면 키위가 되고 뒤집으면 키위새가 되는 인형 ...???? 너무 갖고 싶었는데 뽑을라니까 들고 놔버리더라 지미십사스것 ㅇㄴ 걍 나와버렸는데 배고파서 밥 레이더 떴음 오옹 여러분들이 드시는 라멘은 12시간 이상의 과정을 거쳐 제공 됩니다 .. 먹다가 한참 뒤에 발견해놓고 처음에 발견한 척 으흠 !~ 무료 곱배기가 되니까 개꿀이랍시고 바로 해달라해쑤 히히 물을 따르고 수저를 내두는데 아니 몽키 같은 거만 있지 ... 숟가락이 없으니까 모지모지 싶은거임 으음 ...??? 그냥 기다리기로 함 ㅎㅎㅎ 같이 담겨져서 오더라구 ? 우왕 맛있겠당 돈코츠 라멘은 옳다 와 근데 진짜 국물이 진하고 12시간 끓인 듯한 진한 맛이 나는데 한가지 이상한 점이 있었는데 난 곱배기 치곤 양이 적다고 생각했거든 알고보니까 친구랑 나랑 바꼈음 ㅋㅋㅋ ㅋㅋㅋㅋㅋ ㅋㅋㅋㅋㅋㅋㅋㅋ 사장님이 이게 곱배기래서 먹고 있었눈딩 ㅋㅋㅋㅋ ㅋㅋㅋㅋㅋㅋㅋㅋㅋㅋ 그제야 알아차리고 바꿔서 다시 먹었3 완멘 - 넘 추워서 집 드가기 전에 지하상가 들어갔삼 ㅋㅋㅋㅋㅋㅋㅋㅋㅋㅋㅋ ㅋㅋㅋㅋㅋㅋㅋㅋㅋㅋㅋㅋㅋㅋㅋㅋㅋㅋㅋ 모나리자 볼따구 바람도 넣고 실은 은행에 할 일이 있어서 지하철을 타고 갈라는데... ",
      "char_count": 948,
      "image_count": 32,
      "hashtag_count": 0,
      "has_phone": false,
      "has_naver_reservation": false,
      "recency_penalty": false,
      "weight": 1.0,
      "flags": []
    },
    {
      "id": 27,
      "blog_id": "santoriofsantori",
      "log_no": "223802975601",
      "url": "https://m.blog.naver.com/santoriofsantori/223802975601",
      "date": "2025-03-20",
      "date_raw": "25.3.20.목",
      "title": "천안터미널 라멘 맛집! 멘야마쯔리 신부점 추천!!",
      "author": "추천요정 토리맘",
      "body": "안녕하세용, 요즘은 출산 전에 매운 걸 미리 먹어두자 하는 마음으로 정말 열~~심히 외식을 하고 있는데용! (포스팅할 거리가 엄청 쌓여있어요) 그중에서도 오늘은 멘야마쯔리에 다녀온 걸 포스팅하려구 합니다! 위치는 천안터미널쪽에 있는데 정확히는 신부동 랜드마크타워 옆에 있는 씨유 매장 옆에 있어요! 요기인데용! 단독 건물이지만 내부는 다소 아담한 편입니당! 테이블이 10개정도 되구 옆테이블하고 간격이 가까운 편이에요! 오픈은 11시, 마감은 21시구용 마지막주문은 20시10분까지 가능하구 매주 월요일은 정기 휴무입니다 런치타임 이벤트를 진행하는데요! 라멘류 주문 고객에 한해 런치타임에 사이즈업을 진행해 줍니다! 저는 런치에 방문했지만 정식을 먹어서 따로 사이즈업을 하지는 않았어요! *런치타임 11시~15시* 메뉴판은 태블릿으로 확인할 수 있구요! 태블릿으로 주문하고 나갈 때 결제하면 됩니다. 런치 사이즈업 이벤트 참여할 분들은 왼쪽에 런치단품 탭에서 메뉴를 선택하시면 됩니다. 저는 정식세트탭에서 카라구찌 차항세트를 주문했어요! 카라구찌 차항세트는 14,500원이구요! 카라구찌 라멘은 매운맛을 1~3단계 선택할 수 있어서 저는 2단계 선택했어요! 1단계가 신라면 수준, 2단계가 신라면 2~3배라고 하는데 제 입맛에는 전혀 맵지 않더라구용! 테이블은 요렇게 셋팅돼 있구요! 물은 시원한 차 종류의 물을 가져다 주시는데 보리차인가 무난한 맛이어서 시원하게 마셨습니다. 마늘 다지기와 마늘이 5알 정도 있어서 필요에 따라 넣어드시면 됩니다! 반찬으로는 생강절임이 있는데 저게 라면하고 먹으면 아주 별미입니당! 점심시간에 방문해서 사람이 꽤 있는 편이라 매장 테이블 사진을 못 찍고 내부 일부만 사진을 남겨봤습니다- 라멘 한그릇에 12시간 이상의 과정을 거친다니 역시 맛집은 괜히 맛집이 아니네요! 저는 웨이팅 없이 들어갔지만 입구에 대기 작성표두 있구, 계속 재방문 하게 되는 게 멘야마쯔리는 맛집이 분명합니다 카라구찌 라멘 2단계가 나왔구용! 차슈 3쪽이랑 계란은 기본으로 들어있어요! 멘야마쯔리는 나름 여러번 간 맛집인뎅 갈때마다 요 계란 익힘 상태가 좋습니다. 반숙으로 딱 라면과 알맞게 익어 국물 한숟가락 같이 먹으면 재방문을 다짐하게 된달까요 ㅎㅎ 마늘을 넣고 섞어줬어요! 저는 개취로 마늘 없는 라멘은 상상할 수 없는지라, 요번엔 두 알 넣어줬습니다 ㅎㅎ 맛은 역시나! 꾸준히 재방문하게 되는 맛입니다! 사실 여기 말구두 터미널에 좋아하는 라멘 집이 있었는데... ",
      "char_count": 946,
      "image_count": 23,
      "hashtag_count": 0,
      "has_phone": false,
      "has_naver_reservation": false,
      "recency_penalty": false,
      "weight": 1.0,
      "flags": []
    },
    {
      "id": 28,
      "blog_id": "yumyum0820",
      "log_no": "223799406679",
      "url": "https://m.blog.naver.com/yumyum0820/223799406679",
      "date": "2025-03-17",
      "date_raw": "25.3.17.월",
      "title": "[천안 신부동 라멘] 신부동 점심 메뉴  추천 천안 라멘 맛집 멘야마쯔리 내돈내산",
      "author": "얌얌이",
      "body": "멘야마쯔리 신부점 0507-1381-6907 영업시간 매일 11:00~21:00 15:00~16:30 브레이크 타임 라스트오더 20:10 매주 월요일 휴무 안녕하세요~! 천안 신부동에 위치한 멘야마쯔리에 다녀왔어요 멘야마쯔리 신부점은 정말 오랜시간동안 살아남은 라멘집이에요! 학생시절부터 지금까지 종종 이용하던 식당입니다 홀 내부 테이블 수는 많지 않은 편이에요 7개정도 있어요! 다만 음식이 빨리 나오기때문에 회전율이 엄청 좋은 편이에요 화장실은 안쪽 문으로 열고 나가서 쭉 가다보면 있어요 멘야마쯔리는 적립도 가능하기때문에 계산하실때 만들어서 적립하는 걸 추천해요 테이블엔 마늘, 후추, 깨 등등이 있어요 마늘을 라멘에 으깨서 넣으면 맛있어요ㅎㅎ 네이버 리뷰이벤트도 하고있네요! 멘야마쯔리 메뉴에요!! 시간이 지날수록 추가되는 메뉴와 사라지는 메뉴도 있는 것 같아요 오랜만에 방문하니 사이드가 많이 생겨서 좋네요ㅎㅎ 점심시간에 방문하면 무료로 곱빼기로 먹을 수 있으니 점심시간 방문을 추천드려요 저희는 돈코츠라멘과 멘야 미소라멘을 주문했어요! 멘야마쯔리는 얇은 라멘면이고 멘야미소라멘도 베이스는 돈코츠이기 때문에 취향타지않고 무난하게 먹을 수 있어요 돈코츠 베이스에 된장을 넣어 구수하고 깊은 맛을 내더라구요ㅎㅎ 도전해볼만 한 맛이에요 돈코츠 라멘은 딱 근본의 맛이에요 정석같은 느낌이에요 멘야마쯔리 차슈는 두껍진않지만 부드럽고 불향이 입혀져있어서 차슈만 먹어도 너무 맛있어요ㅜㅜ 추가할걸 그랬네요 계란은 생각보다 간이 밍밍해서 조금 아쉬웠어요 반숙계란이 라멘과 함께 먹기 좋았어요 신부동 데이트 하시거나 점심식사 하러가실때 멘야마쯔리 추천드려요 여기는 마제소바도 정말 맛있으니 꼭 드셔보세요! #천안맛집 #천안터미널맛집 #천안신부동맛집 #천안날씨 #천안라멘 #천안라멘맛집 #답방 #좋아요 #소통 #공감 #댓글 #블로그서이추 #신부동분위기좋은식당 #서이추 #서이추대환영 #서이추환영",
      "char_count": 752,
      "image_count": 12,
      "hashtag_count": 16,
      "has_phone": true,
      "has_naver_reservation": false,
      "recency_penalty": false,
      "weight": 1.0,
      "flags": []
    },
    {
      "id": 29,
      "blog_id": "nokangno1071",
      "log_no": "223795971204",
      "url": "https://m.blog.naver.com/nokangno1071/223795971204",
      "date": "2025-03-14",
      "date_raw": "25.3.14.금",
      "title": "[천안맛집] 천안 신부동 라멘맛집 멘야마쯔리 혼밥 맛집",
      "author": "maianimo",
      "body": "천안 신부동 맛집 멘야마쯔리 천안 신부동 맛집 신부동 혼밥 맛집 천안 라멘 맛집 천안 신부동 라멘 맛집 멘야마쯔리 멘야마쯔리 신부점 충남 천안시 동남구 만남로 18 휴먼빌딩 1층 *영업시간* 11:00-21:00 브레이크 타임 15:00-16:30 (월 정기휴무) 제가 나름 자주 먹고 좋아라하는 음식 중 하나가 라멘인데요. 특히나 혼밥을 하게 되면 라멘만한게 없단 말이죱 보통은 국물있는 돈코츠 라멘을 즐겨 먹는데 오늘은 왜이리 마제소바가 떙기는지 올만에 마제소바 쿨타임 채우러 다녀왔슴다. 천안 라멘 맛집 신부동 혼밥맛집 멘야마쯔리 신부점입니다. 식기와 마늘, 반찬이 준비되어 있어요. 돈코츠 라멘엔 마늘 필수인데 오늘은 마제소바라 저친구를 추가할 일은 없네요. 주문은 테이블에 놓여진 태블릿으로 할 수 있고 저는 마제소바 기본맛으로 주문했습니다. (매운맛도 있어요) 멘야마쯔리 마제소바 10,500원 신부동 근처에 마제소바 파는곳이 거의 없어서 귀하다 귀해 마제라이스도 무료로 제공됩니다. 마제소바에 밥 추가는 선택이 아닌 필수 갠적으로 다찌석이 좋지만 멘야마쯔리 신부점엔 전부 테이블석 넒게 쓰고 오히려 조하(?) 네이버 영수증 이벤트 네이버 영수증 리뷰 작성시 서비스로 음료수 아지타마고 차슈 중 한가지가 무료로 제공됩니다. 마제소바엔 가 최고시라 서비스로 받은 콜라 얼음컵까지 챙겨 주셔서 세상 시원~ 마제소바도 빠르게 나왔구요. 부추 다진고기 마늘 그리고 뭐시기 가루들 계란노른자까지 맛없없 조합 귀여운 미니 라이스와 다시마 식초도 같이 준비완 골고루 샤샤샤샤샥 비벼서 맛있게 념념굿~~~ 올만에 먹으니까 진짜 너무 맛있었음 보통 먹다가 배부르기 전에 좀 물리는 음식 중 하나였는데 파 마늘이 적당히 느끼한 맛을 잡아줘서 이번엔 배부를때까지 다 맛있게 먹음 중간에 다시마 식초도 넣어주고 밥도 비벼 먹어주면 꿀맛 다시마 식초를 다 뿌리면 원래 맛으로 돌아올 수 없으니 꼭 식초없이 드시다가 중간에 뿌려주세요. 저는 식초 뿌린거 먹다가 원래 맛을 또 찾는 사람이라 반쪽만 뿌려둠ㅋㅋㅋ 동글동글 작고 귀여운 미니 라이스 남은 양념에 밥도 꼭 비벼서 드셔보세요.",
      "char_count": 797,
      "image_count": 19,
      "hashtag_count": 0,
      "has_phone": false,
      "has_naver_reservation": false,
      "recency_penalty": false,
      "weight": 1.0,
      "flags": []
    },
    {
      "id": 30,
      "blog_id": "ongjim",
      "log_no": "223795935875",
      "url": "https://m.blog.naver.com/ongjim/223795935875",
      "date": "2025-03-14",
      "date_raw": "25.3.14.금",
      "title": "[천안] 신부동 라멘, 전국 최초 화산라멘, 멘야마쯔리 천안 신부점",
      "author": "옹짐이",
      "body": "천안라멘 멘야마쯔리 천안 신부점에 다녀왔어요. 천안라멘집 멘야마쯔리만의 특별한 시그니처 메뉴인 화산라멘이 있다고 해서 기대를 가득하고 방문했어요. 멘야마쯔리 신부점 영업시간 11:00 - 21:00 브레이크 타임 15:00 - 16:30 위치 내부 내부 공간은 넓지는 않았어요. 단체로 가기에는 조금 좁은 느낌이 있었어요. 커플, 친구끼리 방문하기 좋은 장소예요. 라멘에 통마늘을 으깨먹을 수 있어요. 직접 통마늘을 으깨 먹는다는 게 새로운 느낌이었어요. 화산 라멘(돌솥), 돈코츠 라멘, 카라구찌 라멘, 마제소바 등 여러 메뉴가 있었어요. 저희는 화산라멘(돌솥) 1단계와 2단계, 교자만두를 주문했어요. 천안라멘 가게 테이블에 통깨와, 통마늘, 초생강이 준비되어 있어요. 주문메뉴 사이드 메뉴로 교자만두도 주문했어요. 속에 고기가 들어있는 만두였어요. 기대하던 천안라멘 멘야마쯔리만의 시그니처메뉴 화산라멘이 나왔어요. 직원분이 같이 나온 국물을 뜨거운 돌솥에 넣고 뚜껑을 닫아 줍니다. 모래시계가 내려가는동안 돌솥에서 보글보글 끓고 있어요. 모래시계가 끝나면 불러달라고 하셨어요. 수증기 나오는 모습이 정말 화산 같아요. 돌솥이 엄청 엄청 뜨거운가 봐요. !!뜨거움주의!! 뚜껑을 열면 라멘 국물이 보글보글 끓고 있어요. 보는 맛도 있는 천안라멘 멘야마쯔리 1단계와 2단계를 모두 먹어봤는데 1단계도 상당히 맵더라고요. 불닭볶음면 잘 먹는 편인데 2단계도 많이 맵게 느껴졌어요. 3단계 먹었으면 아마 못 먹었을 거 같아요. 차슈도 부들부들 맛있었어요. 이케차슈를 같이 넣어먹으면 국물이 진해진다고 해서 넣어 먹었어요. 통마늘을 열심히 으깨어 넣어 먹었어요. 마늘을 넣고 안 넣고의 맛 차이가 상당하더라고요. 화산라멘 면발이 기본라멘이랑 다르더라고요. 더 통통한 면발이에요. 반숙란도 같이 주문했는데 반숙란의 표본인 느낌이에요. 맛있게 먹었어요. 계란이 조금 차가워서 라멘에 잠깐 넣었다 드시는 걸 추천드려요.",
      "char_count": 749,
      "image_count": 23,
      "hashtag_count": 0,
      "has_phone": false,
      "has_naver_reservation": false,
      "recency_penalty": false,
      "weight": 1.0,
      "flags": []
    },
    {
      "id": 31,
      "blog_id": "saeunlala",
      "log_no": "223774337338",
      "url": "https://m.blog.naver.com/saeunlala/223774337338",
      "date": "2025-02-26",
      "date_raw": "25.2.26.수",
      "title": "천안 가볼 만한 곳; 멘야마쯔리",
      "author": "사이의 개인적인 취향",
      "body": "일본라멘이 생각날 때면 가는 곳입니다 저는 천안에서는 라멘 먹으러는 이곳만 가는 편입니다 멘야마쯔리 신부점 - 화요일~일요일 11:00~ 21:00 - 브레이크 타임 15:00~16:30 - 매주 월요일 정기 휴무 쌍용점도 가보았는데 거기도 사람이 많더라고요 제가 주로 가는 곳은 신부점입니다 출처: 네이버 메뉴판을 찍어오지 않아서 네이버에서 가져왔습니다 출처: 네이버 평일 런치 타임에는 세트 메뉴도 있다고 하니 참고하시면 좋을 것 같습니다 혼밥 하기에도 좋은 곳이어서 제가 혼밥 하러 가는 곳이기도 합니다 #라멘 맛있게 먹는 법도 한번 읽어줍니다 저는 보통 후추만 좀 더 넣어서 먹는 편입니다 시그니처 메뉴가 화산라멘이라고 하는데 맵찔이인 저는 엄두가 안 나서 늘 돈코츠라멘으로 주문합니다 주문하면 빠른 시간에 라멘이 나와서 점심시간에 후딱 먹기에도 참 좋습니다 차슈가 얇은 편이지만 부드럽고 잡내가 없어서 좋습니다 뽀얗고 진한 국물은 언제 먹어도 맛있습니다 면도 적당해서 후루룩 먹기에 좋습니다 (제 사진 초점은 언제쯤 좋아질까요) 반숙란은 반으로 갈라서 면과 같이 먹으면 꿀맛입니다 간단하면서 따뜻하게 한 끼 하기에 좋은 음식이 라멘 같습니다 ✔️ 천안에서 가장 많이들 가시는 일본라멘집이라고 생각합니다",
      "char_count": 473,
      "image_count": 18,
      "hashtag_count": 1,
      "has_phone": false,
      "has_naver_reservation": false,
      "recency_penalty": false,
      "weight": 1.0,
      "flags": []
    },
    {
      "id": 32,
      "blog_id": "pjskg22",
      "log_no": "223769832706",
      "url": "https://m.blog.naver.com/pjskg22/223769832706",
      "date": "2025-02-22",
      "date_raw": "25.2.22.토",
      "title": "천안터미널 야우리 신부동 라멘맛집 멘야마쯔리 재재재방문!",
      "author": "마리",
      "body": "멘야마쯔리 신부점 천안에서 제일 맛있게먹은 라멘집 멘야마쯔리입니다! 진짜 맛있다고 장담할 수 있는 라멘집이에요!!!! 거진 7,8년을 알고지냈답니다... 계속 장사해주셔서 감사하따름이에요ㅠㅠㅠ 멘야마쯔리 메뉴 중에서는 카라구찌 라멘이 진짜 맛있어요. 매운 라멘인데 단계별로 주문할 수 있어요. 저는 맵찔이라서 1단계로만 먹는답니다.. 그 이상은... 핵매움... 테이블이 예전이랑 다르게 쾌적해졌어요! 물이 보리차여서 너무 좋아요 ㅎㅎ 어릴땐 보리차가 싫었는데 어른되니까... 이것만큼 구수한게 없다... 멘야마쯔리는 기호에 맞게 직접 마늘을 빻아서 넣어 먹을 수도 있어요. 저는 안넣어먹는걸 선호하는 편! 차슈도 추가해서 주문했어요! 멘야마쯔리가 좋은점이 계란 한알을 다 준다는점....!!! 다른데는 거의 반쪼가리만 주는데ㅠ 카라구찌 라멘 해장할 때 먹으면 지인짜 기가막혀요... 그리고 제가 유일하게 밥말아먹는걸 좋아하는 라멘입니다ㅠㅠ 매장에서는 배불러서 못먹지만 배달시켜먹을 땐 꼭 밥을 조금이라도 말아먹을 정도로...중독 쩝니다... 천안오시면 멘야마쯔리 강추합니다!!!!",
      "char_count": 441,
      "image_count": 7,
      "hashtag_count": 0,
      "has_phone": false,
      "has_naver_reservation": false,
      "recency_penalty": false,
      "weight": 1.0,
      "flags": []
    },
    {
      "id": 33,
      "blog_id": "jinjin974",
      "log_no": "223764753280",
      "url": "https://m.blog.naver.com/jinjin974/223764753280",
      "date": "2025-02-18",
      "date_raw": "25.2.18.화",
      "title": "천안 신부동 라멘 맛집, 멘야마쯔리 후기",
      "author": "포포도",
      "body": "안녕하세요 포포도입니다. 천안 신부동에 라멘 맛집이 있다는 거 알고 계셨을까요? 저도 이번에 채또가 데려가 줘서 알게 된 곳인데 채또가 맛집이라고 하니 블로그 글 올릴 거 하나 생겼네!라고 생각하면서 사진을 찍었습니다 ㅎㅎㅎ 천안 신부동 라멘 맛집, 멘야마쯔리 후기 한번 보러 가볼까요? 천안 신부동 라멘 맛집, 멘야마쯔리 후기 음식점: 멘야마쯔리  위치 | 충남 천안시 동남구 만남로 18 휴먼빌딩 1층 ⏰ 영업시간 | 화~일 11:00 ~21:00 /브레이크 타임: 15:00 ~ 16:30 / 라스트 오더: 20:10 / 월요일 정기휴무 ☎️ 전화번호 ㅣ0507-1381-6907 그 외 정보 :포장, 무선 인터넷, 남/녀 화장실 구분, 배달, 단체 이용 가능 (천안 신부동 라멘 맛집, 멘야마쯔리 후기) 매장 외부는 이렇게 일본 느낌 나는 매장 외부였습니다! 장소 멘야마쯔리 위치는 천안 신부동에 있고 신세계백화점과 천안 고속버스터미널, 이마트와도 가깝기 때문에 근처 라멘 맛집을 찾고 계신다면 방문하시는 것도 좋아 보여요! 메뉴 멘야마쯔리는 여기저기 매장이 많은데 초반에는 돈코츠라멘과 카라구찌 라멘으로 많은 사랑을 받았다고 합니다! 라멘집에 보통 메뉴가 이렇게 많지는 않은데 멘야마쯔리는 메뉴가 정말 다양한 거 같아요! 강렬한 매운맛에 화산 라멘, 멘야 마제소바, 차항(일본식 볶음밥), 볼카츠, 미소라멘 등 정말 다양한 메뉴가 있습니다. 런치 타임 이벤트도 있어요! 평일 1인 1 식을 하시는 고객님께는 사이즈 업을 해주신다고 합니다! 아니 이러면 혼밥 하러 가도 너무 좋은데요..? 저희가 주문한 메뉴 - 카라구찌라멘 ( 2단계) 저와 채또는 매운라멘인 카라구찌라멘 2단계를 먹었어요! 다음에 또 방문하면 사이드도 한번 주문해서 먹어봐야겠어요! 매장 내부 라멘집답게 오픈 주방입니다! 이런 맛에 라멘집 가는 거 같기도요? 개인적으로 라멘집 매장은 항상 넓지는 않았던 거 같아요! 멘야마쯔리도 매장 내부는 크지 않았습니다! 4인 테이블 5개에 2인 테이블 2개 정도였어요! 수저를 꺼내려고 열어봤는데 엥 마늘 다지기가 있더라고요? 근데 설마.. 이거 모르시는 분들 있을까요..? 마늘 다지기, 마늘 빻기 해주는 물건인데 저 안에다가 마늘을 넣고 손아귀 힘으로 힘을 주면 마늘을 쉽게 다질 수 있습니다! 테이블 위에는 이렇게 마늘도 있었어요! 마늘 넣는 게 취향이신 분들은 마늘을 빻아서 넣어도 맛있을 거 같네요! 네이버 리뷰 이벤트도 있으니 한번 확인해 보시고 이벤트도 꼭 참여해 보세요! 후기 비주얼이 미쳐버리는 카라구찌라멘이 나왔습니다! 육수 색이... ",
      "char_count": 966,
      "image_count": 18,
      "hashtag_count": 0,
      "has_phone": true,
      "has_naver_reservation": false,
      "recency_penalty": false,
      "weight": 1.0,
      "flags": []
    },
    {
      "id": 34,
      "blog_id": "ppoigom",
      "log_no": "223761113142",
      "url": "https://m.blog.naver.com/ppoigom/223761113142",
      "date": "2025-02-15",
      "date_raw": "25.2.15.토",
      "title": "일본식 수제 라멘 천안 신부동 맛집 ‘멘야마쯔리’",
      "author": "잇몸만개얄",
      "body": "멘야마쯔리 충남 천안시 동남구 만남로 18 휴먼빌딩 1층 화~일 11:00~21:00 15:00~16:30 브레이크타임 20:10 라스트오더 ✔️ 월요일 정기휴무 근처 공용 주차장 이용 외관 충남 천안시 동남구 만남로 18 휴먼빌딩 1층 안녕하세요:) 오늘은 천안 신부동에 위치한 ‘멘야마쯔리’에 방문했습니다아! 내부 충남 천안시 동남구 만남로 18 휴먼빌딩 1층 테이블은 7개 정도 있고 매장은 조그만한 편입니다아! 메뉴판 충남 천안시 동남구 만남로 18 휴먼빌딩 1층 메뉴 먼저 보고 가실게요:) 깊고 진한 맛을 가지고 있는 멘야마쯔리 !! 대표메뉴는 화산라멘, 돈코츠, 카라구찌 라멘이 있어요 하카타 돈코츠라멘 - 9,000원 A-3 세트 - 14,000원 (돈코츠라멘+볼카츠 2조각) 요렇게 주문했습니다아! 맛을 보아요 충남 천안시 동남구 만남로 18 휴먼빌딩 1층 돈코츠라멘 두둥! 차슈 3개, 간장계란, 숙주, 파 등이 들어가고 국물이 찐해서 맛있었어요~ 여러분, 여기 고로케 맛집인거 같아요오! 고로케 한입을 따악 먹으면 고기 듬뿍 들어있는게 느껴질 정도록 고기가 왕창 들어있슴당 여기까지 천안 신부동에 위치한 '멘야마쯔리' 후기였습니다아 돈코츠라멘이 생각이 나서 방문한 멘야마쯔리 고기 육수의 진한 맛과 간장계란이 킥이였어요~ 양이 많은 편은 아니지만 점심에 먹기 딱 좋은 곳이고 특히, 혼밥하기 넘 좋은 곳인 것 같아요 ㅎㅎ 오늘도 잘 먹었습니다아 #천안신부동맛집 #천안맛집 #멘야마쯔리 #천안라멘맛집 #천안가볼만한곳 #천안터미널맛집 #천안돈코츠라멘",
      "char_count": 595,
      "image_count": 13,
      "hashtag_count": 7,
      "has_phone": false,
      "has_naver_reservation": false,
      "recency_penalty": false,
      "weight": 1.0,
      "flags": []
    },
    {
      "id": 35,
      "blog_id": "chang_051423",
      "log_no": "223752143172",
      "url": "https://m.blog.naver.com/chang_051423/223752143172",
      "date": "2025-02-08",
      "date_raw": "25.2.8.토",
      "title": "[일상로그] 짧지만 즐거웠던 천안여행☁️",
      "author": "챙이",
      "body": "친구와 천안역에서 만나 신부동으로 이동했다. 둘 다 배가 너무 고파서 먼저 밥을 먹기로 했다. 메뉴는 라멘! 멘야마쯔리에서 라멘을 먹었다. 난 유명한 화산 라멘을 먹었다. 맵기 단계는 1단계로 했는데 내 입맛에는 조금 매웠지만 못 먹을 정도는 아니어서 맛있게 먹었다. 밥을 먹고 배가 너무 불러서 교보문구에 가서 소화 시킬 겸 구경을 했다. 공책도 보고 편지지도 보고 책도 봤다. 오랜만에 교보문구를 구경해서 즐거웠다. 교보문구를 다 구경한 후에 카페를 갔다. 원래 가기로 찜해둔 카페가 있었는데 들어가니 만석이라 나와서 ’피오르드’라는 카페에 갔다. 빵이랑 음료 둘 다 정말 맛있었다. 다음에 또 방문할 예정이다! 카페에서 시간을 보낸 후에 근처에 있는 소품샵을 구경하며 시간을 보냈다. 그리고 스티커 사진을 찍을 수 있는 곳이 있어 같이 스티커 사진을 찍고 이쁘게 직접 꾸몄다. 굉장히 재미있게 사진 찍고 꾸몄다. 이렇게 시간을 보내다 저녁을 먹었다. 저녁은 ‘그노브’라는 식당에 갔다. 뇨끼와 라자냐를 시켜서 나눠 먹었다. 라자냐는 처음 먹어봤는데 생각보다 맛있었다. 뇨끼는 몇 번 먹어봤는데 먹어본 곳 중에 손에 꼽을 정도로 맛있었다. 크림소스가 별로 느끼하지도 않고 딱 좋았다. 이렇게 저녁을 먹고 친구와 헤어져 각자 집으로 갔다. 오랜만에 밖에서 친구를 만나 신났고 또 몇 개월 만에 본 친구라 더 반갑고 좋았다. 맛있는 것도 많이 먹고 굉장히 즐거운 하루를 보내 만족스러웠다!",
      "char_count": 538,
      "image_count": 4,
      "hashtag_count": 0,
      "has_phone": false,
      "has_naver_reservation": false,
      "recency_penalty": false,
      "weight": 1.0,
      "flags": []
    },
    {
      "id": 36,
      "blog_id": "cottoncandy_cat",
      "log_no": "223734496983",
      "url": "https://m.blog.naver.com/cottoncandy_cat/223734496983",
      "date": "2025-01-22",
      "date_raw": "25.1.22.수",
      "title": "천안 신부동 라멘 맛집 멘야마쯔리 내돈내산, 난 여기 라멘이 젤 좋아",
      "author": "윤집사",
      "body": "시작부터 완멘 샷- ㅋㅋㅋㅋㅋㅋㅋㅋㅋㅋㅋㅋㅋㅋㅋㅋㅋㅋㅋㅋㅋㅋㅋㅋ 화산라멘 12,000 돈코츠라멘 9,500 카라구찌, 미소 10,000 마제소바 10,500 여기에 볼카츠와 교자, 오코노미야끼 등 사이드와 라멘 세트도 다양하게 있어요 윤집사는 언제나 화산 or 매운라멘 파입니다 화산라멘 포스팅은 요기 있습니다! 오늘은 카라구찌라멘이 땡겼어요 화산라멘이 묵직하고 진하다면 매운라멘은 개운하게 매운 맛이랄까? 맛이 결코 가볍지는 않은데 개운하고 얼큰한게 해장으로 그만이에요 하 쒸 이거지............ 계란 노른자의 완벽한 익힘 보시라고요 잠실 오레노라멘 갔다 실망한 위장 멘야마쯔리에서 회복하고 감 진짜 여기가 미슐랭이면 멘야마쯔리는 쓰리스타 달아야함 저는 계란을 호로록 먹는것보단 받자마자 이렇게 찢어서 국물에 스며들게끔 먹는걸 좋아해요 매운라멘에 빠질 수 없는 멘마추가! 멘마 꼭 추가해서 드세요 이구역 멘마 귀신이 나임 아니 어지간하면 이렇게 국물 싹싹 비우진 않는뎈ㅋㅋㅋㅋㅋㅋㅋㅋㅋㅋㅋㅋㅋㅋ 민망할 정도로 깨끗...... 다른 후기 보면 자리 많은데 4인석 안줬다고 징징대는 사람들 많던데 이해 안감 실제로 저 먹을때도 한가한듯 싶었는데 한순간에 만석되고 그런적 많음 앉으란데 앉읍시다 자리안내받고 들어가는건 요새 기본 아닌가요 직원분들도 왕왕 친절하시고 천안 최고 라멘 맛집을 찾으신다면 멘야마쯔리 강력추천 합니다! 천안 신부동 라멘맛집 멘야마쯔리 내돈내산 후기였습니다 서이추는 언제나 환영 댓글답방은 100% 갑니다 ❤️",
      "char_count": 591,
      "image_count": 9,
      "hashtag_count": 0,
      "has_phone": false,
      "has_naver_reservation": false,
      "recency_penalty": false,
      "weight": 1.0,
      "flags": []
    },
    {
      "id": 37,
      "blog_id": "yoondh0705",
      "log_no": "223730015735",
      "url": "https://m.blog.naver.com/yoondh0705/223730015735",
      "date": "2025-01-18",
      "date_raw": "25.1.18.토",
      "title": "It's been a while since I posted my daily life in January⁺. ⊹˚₊ ₊·(੭  · ˕ · )੭‧*",
      "author": "윤뿡뿡",
      "body": "2025 첫 일상글! 뭔가 많은걸 했지만 한게 없는.. 부지런하게 사는게 25년도 목표인데 아직도 게으른 베짱이라는 요건 귀여워서 넣는 사진 귀여운 쥬닝언니가 커피사고 받아온 과자꾸러미를 콩한쪽도 나눠먹는 우리라며 큐티클걸즈 맴바들에게 하나씩 배분 ㅎㅎ 귀여운 주닝이언니 25년도 야무지게 귀여워버려! 오랜만에 지은이 만나는날 둘다 통해서 저녁은 멘야마쯔리 여기 화산라멘이 그렇게 맛있다고 해서 방문 했는데 그냥 그랬다는 ! 아직 내맘속 1위 ㅁㅇㅌㅁㅅ 지은이가 수풀레가 먹고싶다고 해서 오랜만에 카페어젠 수플레 케이크 오랜만에 먹으니 너무 부드럽고 맛있더라 .. 비주얼도 예쁜 수플레케이크.. 왕맛 분위기 좋은 카페어젠은 덤 언제 이렇게 큰거야 내조카 귀엽고 이쁘고 사랑스럽고 난리 이날 사랑 독차지 햇던 사랑둥이 아가 가족들이랑 다같이 사네피크닉 가족들이랑 다같이 텐텐깔아서 텐텐했느데 어찌나 잼던지.. 역시 줌마스러운 웃김은 이기지 못해.. 사네 이벤트 중이라 한시간 추가이용에 스콘이랑 빵도 주심 ! 커피도 맛있고 분위기도 너무 좋은 사네:-) 세시간중 두시간을 텐텐으로 불태웟더니 배고파졌자나 !? 이마시야 먹고 싶었는데 휴무 이슈로 배부장 배부장 오랜만에 먹으니 칼칼하니 존맛탱 같이 시킨 계란말이는 필수 일상 별거 없더니 사진도 정말 별거 없네 ㅎㅎ 다음 일상은 사진 꽉꽉 채워서 야무지게 올려야지 ! :-ㅇ #일상글 #소통 #서이추 #서이추환영",
      "char_count": 540,
      "image_count": 15,
      "hashtag_count": 4,
      "has_phone": false,
      "has_naver_reservation": false,
      "recency_penalty": false,
      "weight": 1.0,
      "flags": []
    },
    {
      "id": 38,
      "blog_id": "eh_old",
      "log_no": "223716124981",
      "url": "https://m.blog.naver.com/eh_old/223716124981",
      "date": "2025-01-06",
      "date_raw": "25.1.6.월",
      "title": "천안 신부동 마제소바 맛집 '멘야마쯔리 신부점' 내돈내산 후기",
      "author": "키위위키",
      "body": "지난주에는~ 천안 종합터미널 근처 천안 신부동 맛집 멘야마쯔리 신부점 다녀왓슴니다 가게 입장~ 제가 갔을 때가 11시인가 11시 반이었나... 첫 손님이엇슴ㅎ 안쪽에서 보면 요로코롬 자리가 더 잇구용 라멘은...정성이다... 장인정신... 앞에서는 직원분들이 조리하는게 보입니다ㅎ 화장실은 가게 안쪽 문을 열고 나가서 건너편에 있는 건물에 잇슴ㅎ 테이블에 자리잡앗구용 물은 차 종류구용 마제소바에 빠지면 섭한 다시마식초 잇구용 메뉴판 구경~ 햇지만 오늘은 마제소바 머그러왓기에 마제소바 주문~ 미니밥도 무료 추가 가능합니다ㅎ 요 직접 마늘을 다지는 도구랑 깨/양파?마늘?가루도 잇섯슴ㅎ 그러면 오늘의 주인공 천안 신부동 마제소바 맛집 멘야마쯔리의 마제소바 등장~ 그런데 이제 미니밥을 곁들인ㅎ 노른자 어쩜 이리 탱글하게 잘 해놓으시는지ㅎ 그러면 마구마구 섞어주공 마늘도 좀 넣어주공~ 생각보다 잘 안대더라구용ㅎ 오랜만에 써바서 근감ㅎ 이 고소~하고 살짝 또 꾸덕하면서 가쓰오부시 다진 고기 다진마늘 등등이 어우러지면서 나오는 감칠맛ㅎㅎ 쫙쫙 감기는 천안 신부동 맛집입니다ㅎㅎ 근데 이거 빠지면 안됩니다 바로 다시마식초 다시마식초를 넣어야 감칠맛이 폭발하면서 완벽한 마제소바가 댐ㅎㅎ 요건 영수증 리뷰이벤트로 받은 차슈 토핑ㅎㅎ 더 풍성해진 마제소바~ 차슈는 불맛 + 짭조름한 맛이 좋더라구용 마제소바 먹는 이유) 사실 남은 고명에 밥비벼먹으려고임 비주얼은 그래도~ 이게 진짜 맛도리입니다ㅎㅎ 사실 이 소스에 밥만 볶아도 맛있을듯ㅎㅎ 차슈하나 애껴뒀다가 마지막 밥이랑 야무지게 먹음ㅎㅎ 나갈 때 되니까 모든 테이블이 꽉차더라구용ㄷㄷ 역시 신부동 맛집입니다 천안 신부동 라멘 맛집 멘야마쯔리 다녀왓구용 라멘드시는 분들도 많던디 저는 마제소바 먹었습니다ㅎㅎ 감칠맛 좋고 면도 쫙쫙붙고 간간해서 괜찮더라구용ㅎㅎ 다음에는 매운 맛으로 먹어보고 싶습니다ㅎㅎ #천안신부동맛집 #신부동맛집 #천안마제소바 #신부동마제소바 #신부동라멘 #천안멘야마쯔리 #신부동멘야마쯔리 #마제소바맛집 #내돈내산",
      "char_count": 781,
      "image_count": 33,
      "hashtag_count": 9,
      "has_phone": false,
      "has_naver_reservation": false,
      "recency_penalty": false,
      "weight": 1.0,
      "flags": []
    },
    {
      "id": 39,
      "blog_id": "sifirene0621",
      "log_no": "223714991487",
      "url": "https://m.blog.naver.com/sifirene0621/223714991487",
      "date": "2025-01-05",
      "date_raw": "25.1.5.일",
      "title": "일상기록 no. 11 - 2025⭐️ 근데 이제 이사를 곁들인⭐️",
      "author": "시프시케",
      "body": "때는 아직 2024… 크리스마스 다음날 행복한 연휴 바로 다음날이었는데 아침에 청천벽력같은 소식을 듣고 벌떡 일어남..!! 아뉘… 그…. 남편 출근 전에 내가 챙겨줘야 하는 게 있었는데 까먹어버린 것 ㅠㅠ 안그래도 출퇴근이 멀기 때문에 지금 당장 가지러 오지도 못하고 그거 없으면 일도 못하고ㅠㅜㅠ 바보같은 내자신 ㅠㅠㅠㅠ 출처: 네이버 블로그 남편의 원망어린 목소리가 들려오고 막 나는 어쩔줄을 모르겠고 차로도 먼데 뚜벅이로는 진짜 답도 없는데ㅠㅠㅠ 일단 거의 모든 짐을 챙겨 와다다다 나갔다 내가 미얀네ㅠㅜㅜ 하아 어케 택시-기차-택시 루트를 이용해볼라해도 적어도 두시간~두시간반은 걸렸을 것 같았음 ㅠ 계속 각을 이리저리 보다가 안되겠다ㅜㅜㅜㅜㅜ하고 냅다 택시 부름 ㅋㅋㅋㅋㅋ 와 나 택시타고 고속도로 처음 타봐… 막힐때마다 속이 아주 그냥 바짝바짝 타들어가고ㅠㅠ 하아아아아아 왜 고속도로는 막히는 걸까 왜..!!!!! (너 같은 인간땜에) 안 막힐때마다 마구 밟아주신 기사님…. 정말 감사했습니다~~~ㅠㅠㅠ 처음으로 별점 남겨드린 기사님 안돼애애애애애ㅜㅜㅜㅜㅜㅜ하면서 일단 달림 택시비가 얼마가 나오던 일단 달림 (다행히 잠자던 하나머니 몰빵해서 금액 세이브함) 헥헥 일단 정말 다행인게…!! 진짜 간발의 차로 업무 들가기 전에 전달할 수 있었음 ㅠ (지져스 크라이스트 아리가또 고자이마스) 압도적 감사ㅠ!!! 이것만 전달해주세여 하고 바로 유턴해서 나갈라고 하는데 남편한테 바로 전화 옴 출처: 네이버 블로그 너 어디가니..?? 이래서 ??? 집가려고 하니까 바로 뒷덜미 붙잡힘 근데 얼굴보자마자 눈물 터짐ㅋㅋㅋ ㅠㅠㅠㅠ큐ㅠㅠㅠㅠ 미얀네ㅠㅜㅜㅜㅜㅜㅜ 고멘 ㅠㅠㅠㅜㅠㅠ 흐규흐듀구ㅠ 이러니까 예전에 비해 많이 순해진 남편… 바로 안아주고 토닥토닥해주더라 ㅋㅋ 근데 집으로 갈라하는데 계속 탈출을 못하게 함 (나 이삿짐 싸야하는데) 화는 나도 분리불안인 녀석 음… 결국 점심까지 같이 먹게 됨 ㅋㅋ 메뉴는 온센 텐동/ 카라아게 텐동 점심먹고 갈라는데 또 커피로 날 낚음 쓰읍 또 디저트까지 챙겨주니 이거 뭐 계속 같이 퇴근까지하자고 찡찡거려서 에라 모르겠다 하고 존버함 귀여워 보이면 콩깍진가 ㅋㅋㅋㅋ 언제 택배가 올 지 몰라서 (이사 예정) 일단 남편 주소로 보냈는데 마침 딱 오늘 와섴ㅋㅋ 바로 픽업했다 피팅해봤는데 상당한 박시핏..! 요즘 밀리터리가 넘 죠아서 눈독들이던 바지였는데 신축성은 제로긴 한데 엄청난 박시핏이라 괜찮을 듯 꽤나 빳빳한 재질이라... ",
      "char_count": 931,
      "image_count": 115,
      "hashtag_count": 0,
      "has_phone": false,
      "has_naver_reservation": false,
      "recency_penalty": false,
      "weight": 1.0,
      "flags": []
    },
    {
      "id": 40,
      "blog_id": "bluehen7",
      "log_no": "223714061504",
      "url": "https://m.blog.naver.com/bluehen7/223714061504",
      "date": "2025-01-03",
      "date_raw": "25.1.3.금",
      "title": "오래간만에 맛보는 돈코츠라멘 천안 멘야마쯔리 신부점",
      "author": "트리파파",
      "body": "몇 년 전에 일본 여행에서 먹었던 돈코츠 라멘 맛이 아직도 기억에 남습니다. 아직 국내에서는 그곳을 능가할 만한 라멘집을 찾지 못했지만 가끔씩 들르면서 맛을 찾아보고 있어요. 이번에 방문했던 식당은 맨야마쯔리라는 일식 라멘 프랜차이즈였는데요, 돈코츠 라멘을 먹고 온 후기를 남겨볼까 합니다. … 멘야마쯔리 신부점 · 주소 : 충남 천안시 동남구 만남로 18 1층 · 영업시간 : 11:00 - 21:00 브레이크 타임 15:00 - 16:30 라스트 오더 20:10 · 일본식 라멘 전문점 제가 찾아갔던 멘야마쯔리 신부점은 천안 신부동 신세계 백화점 건너편 먹자골목에 위치하고 있었습니다. 주변에 먹거리는 물론 놀 거리도 많았던 지역으로 기억하고 있어요. 지하철은 천안역과 두정역 중간쯤에 있으니 참고하셔요. 출입구 출입구 모습은 누가 봐도 일식집처럼 꾸며놓은 듯한 외관이었습니다. 나무로 결을 만들어지어놓은 모습은 마치 일본 현지에 있는 식당을 바라보는 기분이었어요. 주차가 어려워요 하지만 이곳은 주차장이 없는 듯. 왼쪽으로 들어가니 아니라고 해서 나왔는데 오른쪽도 아닌 것 같고.. 결국 주변 공영주차장에 주차를 하고 이동하였습니다. 키오스크 식당 내부 사진이 없네요 ㅠㅠ 일단 내부로 들어가니 직원분이 자리를 안내해 주셨습니다. 일본 식당의 경우 아무대나 막 앉는 건 예의가 아니라 하더라고요. 그래서 그런 건지 자리가 불편했지만 그러려니 하고 앉았습니다. 점심 피크 시간도 아니었고 손님도 한 테이블밖에 없었는데 좀 더 편한 자리로 안내해 줬으면 하는 아쉬움이 있었어요. 이후로 손님이 추가로 더 왔는데 안쪽 빈자리를 놔두고 굳이 제 옆자리로 안내를.. 옆옆 테이블에도 손님이 있는데다 테이블까지 좁아 답답했습니다. 돈코츠라멘 돈코츠라멘 9,000원 다른 메뉴는 보지도 않고 돈코츠라멘을 주문했습니다. 키오스크에서 주문할 때 차슈, 계란 등을 선택하는 메뉴가 보였는데요, 기본에 넣어야 하는건지 추가를 하는건지 안내가 안 되어 있더라고요. 일본에서 주문할 때 하나하나 선택 주문했던 게 기억나 돈코츠라멘만 선택하면 밋밋하게 나올까봐 차슈랑 계란을 선택했어요. 그런데 메뉴가 나온 걸 보니 추가 주문이었지 뭐예요 ㅋㅋ 면과 차슈, 계란 이곳 역시 일본에서 먹었던 그 맛 까진 아니었지만, 나름 맛있는 돈코츠라멘이었습니다. 차슈도 그렇고 계란도 반숙란으로 부드러워 좋았어요. 국물도 느끼하면서 묵직한 게 돈코츠라멘다웠습니다. 국물에 검게 생긴건 계란 간장 소스 같은데요, 국물이랑 같이... ",
      "char_count": 940,
      "image_count": 9,
      "hashtag_count": 0,
      "has_phone": false,
      "has_naver_reservation": false,
      "recency_penalty": false,
      "weight": 1.0,
      "flags": []
    },
    {
      "id": 41,
      "blog_id": "ji_eun4215",
      "log_no": "223700330401",
      "url": "https://m.blog.naver.com/ji_eun4215/223700330401",
      "date": "2024-12-27",
      "date_raw": "24.12.27.금",
      "title": "[충남/천안] 신부동 라멘맛집, 멘야마쯔리 후기",
      "author": "양큼",
      "body": "열어분 라멘 좋아하시나요!?? 요즘 추워서 라멘같이 뜨근~허니 국물요리가 많이 땡기실 것 같은데요 제가 천안신부동에서 라멘 맛집을 찾아왔습니다.  주소: 충청남도 천안시 동남구 만남로 18 휴먼빌딩 1층  영업시간: 11:00-21:00(15:00-16:30 브레이크 타임/월요일 휴무) ※ 20:10 라스트오더  전화번호: 0507-1381-6907  주차장여부: x  포장, 무선인터넷, 배달, 단체이용, 유아의자 가능 신부동 앞에 있는 먹자골목에 위치한 멘야마쯔리! 이미 아실만한 분들은 다 아실 것 같아요! 출처: 네이버플레이스 멘야마쯔리 신부점 메뉴판 키오스크로 주문해서 네이버 플레이스에서 가져온 메뉴판,,, 여러분 메뉴판 보시면 뭐가 젤 끌리시나요.. 전 진짜 고민도 안하고 바로 화산라멘 했습니다..ㅋㄷ 멘야마쯔리의 좋은 점!! 맵기 조절 가능~!!!!! 전 바로 상여자기때문에 한라산으로 고고했습니다. 왜냐면 고기육수라서 안매울 것 같았거등요 메뉴가 나오고 진짜 띠용 했습니닼ㅋㅋㅋㅋ 저거 모야,,;;; 당황하고 있으면 사장님께서 육수를 부워주시는데여 면을 약간 설익혀서 뜨거운 육수를 넣고 저 뚜껑을 덮어 약간 후숙..? 뭐라해야하나요..? 암튼 좀 더 익힌다음에 먹는 이색적인 라멘입니다! 화산라멘인 이유는 매워서가 아니라 라멘 뚜꼉에서 화산처럼 연기가 뿜뿜해서였다는 사실~!! 사장님께서 친절하게 타이머를 맞춰주시고 시간이 다되면 뚜껑을 수거해가시는데요 뚜껑을 열면 아주 먹음직스러운 라멘이 땋!!!!!!!!!!!!!! 근데요,, 진짜 매웠습니다. 제가 매운걸 못먹진 않는데 위가 따끔따끔한게 매웠습니다.. 댄싱핑이랑 갔는데 댄싱핑은 먹다가 중도포기하고 저는 가오때문에 다 먹었어요ㅠ 그래도 맛있었지만.. 저거 먹고 3시간 뒤에 화장실에서 심판받았습니다. 진짜 매운거 좋아하시는 분들만 한라산 이상 먹기..ㅠ 그래도 맛있었어요!! 담에 또 기회가 된다면 방문해볼 예정입니다:)",
      "char_count": 753,
      "image_count": 5,
      "hashtag_count": 0,
      "has_phone": true,
      "has_naver_reservation": false,
      "recency_penalty": false,
      "weight": 1.0,
      "flags": []
    },
    {
      "id": 42,
      "blog_id": "flavortrail",
      "log_no": "223691699541",
      "url": "https://m.blog.naver.com/flavortrail/223691699541",
      "date": "2024-12-12",
      "date_raw": "24.12.12.목",
      "title": "천안 터미널 라멘 맛집 멘야마쯔리 솔직 후기",
      "author": "냠냠박사",
      "body": "천안에서 가까운 일본을 느끼자!! 멘야마쯔리 천안 터미널 라멘 맛집 글 사진 Copyright 맛집 블로거 냠냠박사 멘야마쯔리 신부점 위치 : 충남 천안시 동남구 만남로 18 휴먼빌딩 1층ㅋ  영업시간 : 10:30 - 21:20 라스트오더 20:50 월요일 정기휴무  브레이크타임 : 15:00 - 16:30 ️ 주차 정보 : x ✔️ 천안 터미널 근처 라멘집 ✔️ 돼지 냄새 없이 깔끔한 국물 맛 ✔️ 리뷰 이벤트로 차슈 3개 추가 가능 1.위치 천안 고속터미널과 천안 시외버스터미널 근처에 위치해 있어 이동 중 들르기 동선상 좋습니다 ㅎㅎ. 터미널에서 도보로 약 5~10분 거리라 걸어가기에도 부담이 없었습니다. (저는 케리어 1개랑 배낭 1개라 좀 질질 끌고감) 특히 대중교통 이용객들에게도 좋은 위치인데, 터미널 주변에는 다양한 상가와 편의시설이 있어서 짧은 대기 시간 동안 라멘 한 그릇 즐기기 좋았어요. 차량을 이용하는 경우에는 조금 어렵습니다. 방문 후기를 바로 포스팅해볼게요!  2. 인테리어 매장 안으로 들어서자 마치 일본 골목길에 있는 정통 라멘집에 온 듯한 분위기가 느껴졌어요. 내부는 깔끔하면서도정돈된 모습이었고, 나무 소재의 테이블과 따뜻한 조명 덕분에 아늑했습니다. 일본 특유의 소박하면서도 정갈한 감성이 그대로 담긴 인테리어가 인상적이었어요. 조리 과정을 직접 볼 수 있는 오픈 주방은 일본의 전통적인 라멘야(라멘집)에서 볼 법한 구조로, 음식을 기다리며 셰프의 정성스러운 손길을 엿볼 수 있어 좋았습니다. 일단 딱 들어가자마자 일본처럼 특유의 그 돼지 비린내가 나지않은 가게였고, 좌석 간격도 적당히 여유로워 혼자 조용히 라멘을 즐기기에도, 친구와 함께 담소를 나누며 식사하기에도 편안했어요. (저는 혼자갔지만 대부분 친구랑 오셨더라구요) 전체적으로 일본 현지의 라멘집을 그대로 옮겨놓은 듯한 느낌이였습니다. 3. 메뉴 제가 주문한 메뉴는 '돈코츠라멘'이었는데, 가격은 9,000원이었습니다. 점심에 가시면 좋은게 사이즈 업을 해주시더라구요. 냠냠박사인 저는 당연히 추가해서 먹었습니다. 돼지뼈로 우려낸 육수의 맛이 깔끔하게 느껴졌어요. 특히 라멘에서 흔히 걱정하는 돼지고기 특유의 냄새가 전혀 없어서 좋았습니다. 또 하나의 재미있는 점은 리뷰 이벤트를 통해 차슈 3개를 추가로 받을 수 있다는 거예요. (선 결제 하시고, 영수증 리뷰하시면 받을수 있어요!) 서비스로 나온 차슈 덕분에 풍성하게 먹었습니다. 라멘에 들어 있던 계란(타마고)은 진짜 제가 살면서 몇번 안먹어본 좋아하는 스타일의 반숙으로... ",
      "char_count": 958,
      "image_count": 5,
      "hashtag_count": 0,
      "has_phone": false,
      "has_naver_reservation": false,
      "recency_penalty": false,
      "weight": 1.0,
      "flags": []
    }
  ],
  "excluded": [],
  "summary": {
    "total_naver_count": 438,
    "api_max_accessible": 135,
    "total_valid": 42,
    "count_within_18m": 42,
    "count_18m_to_24m": 0,
    "phase2_entered": false,
    "phase2_reason": null,
    "min_target_met": true,
    "max_target_met": false,
    "total_excluded": 0,
    "excluded_paid_hard": 0,
    "flag_paid_suspect": 0,
    "flag_extraction_warn": 2,
    "has_naver_reservation_count": 0,
    "date_oldest": "2024-12-12",
    "date_newest": "2026-06-06"
  }
}